[
	{
		"id": "MTA.LIRR.GO201_26_2701.Weekday",
		"t": "MTA.LIRR.GO201_26_2701",
		"r": "MTA.LIRR.7",
		"n": "2701",
		"y": "MTA.Regional",
		"d": "Inbound",
		"os": [
			"MTA.LIRR.65"
		],
		"tt": [
			{
				"s": "MTA.LIRR.65",
				"d": "00:36"
			},
			{
				"s": "MTA.LIRR.101",
				"d": "00:41"
			},
			{
				"s": "MTA.LIRR.114",
				"d": "00:43"
			},
			{
				"s": "MTA.LIRR.32",
				"d": "00:45"
			},
			{
				"s": "MTA.LIRR.217",
				"d": "00:48"
			},
			{
				"s": "MTA.LIRR.94",
				"d": "00:50"
			},
			{
				"s": "MTA.LIRR.66",
				"d": "00:53"
			},
			{
				"s": "MTA.LIRR.211",
				"d": "00:57"
			},
			{
				"s": "MTA.LIRR.180",
				"d": "01:00"
			},
			{
				"s": "MTA.LIRR.122",
				"d": "01:03"
			},
			{
				"s": "MTA.LIRR.119",
				"d": "01:05"
			},
			{
				"s": "MTA.LIRR.102",
				"d": "01:13"
			},
			{
				"s": "MTA.LIRR.214",
				"d": "01:23"
			},
			{
				"s": "MTA.LIRR.349",
				"d": "01:33"
			}
		]
	},
	{
		"id": "MTA.LIRR.GO201_26_2702.Weekday",
		"t": "MTA.LIRR.GO201_26_2702",
		"r": "MTA.LIRR.7",
		"n": "2702",
		"y": "MTA.Regional",
		"d": "Outbound",
		"os": [
			"MTA.LIRR.349"
		],
		"tt": [
			{
				"s": "MTA.LIRR.349",
				"d": "00:38"
			},
			{
				"s": "MTA.LIRR.55",
				"d": "00:53"
			},
			{
				"s": "MTA.LIRR.107",
				"d": "00:55"
			},
			{
				"s": "MTA.LIRR.102",
				"d": "01:01"
			},
			{
				"s": "MTA.LIRR.119",
				"d": "01:07"
			},
			{
				"s": "MTA.LIRR.122",
				"d": "01:09"
			},
			{
				"s": "MTA.LIRR.180",
				"d": "01:12"
			},
			{
				"s": "MTA.LIRR.211",
				"d": "01:15"
			},
			{
				"s": "MTA.LIRR.66",
				"d": "01:19"
			},
			{
				"s": "MTA.LIRR.94",
				"d": "01:22"
			},
			{
				"s": "MTA.LIRR.217",
				"d": "01:24"
			},
			{
				"s": "MTA.LIRR.32",
				"d": "01:27"
			},
			{
				"s": "MTA.LIRR.114",
				"d": "01:29"
			},
			{
				"s": "MTA.LIRR.101",
				"d": "01:32"
			},
			{
				"s": "MTA.LIRR.65",
				"d": "01:37"
			}
		]
	},
	{
		"id": "MTA.LIRR.GO201_26_2703.Weekday",
		"t": "MTA.LIRR.GO201_26_2703",
		"r": "MTA.LIRR.7",
		"n": "2703",
		"y": "MTA.Regional",
		"d": "Inbound",
		"os": [
			"MTA.LIRR.65"
		],
		"tt": [
			{
				"s": "MTA.LIRR.65",
				"d": "01:06"
			},
			{
				"s": "MTA.LIRR.101",
				"d": "01:11"
			},
			{
				"s": "MTA.LIRR.114",
				"d": "01:13"
			},
			{
				"s": "MTA.LIRR.32",
				"d": "01:15"
			},
			{
				"s": "MTA.LIRR.217",
				"d": "01:18"
			},
			{
				"s": "MTA.LIRR.94",
				"d": "01:20"
			},
			{
				"s": "MTA.LIRR.66",
				"d": "01:23"
			},
			{
				"s": "MTA.LIRR.211",
				"d": "01:27"
			},
			{
				"s": "MTA.LIRR.180",
				"d": "01:30"
			},
			{
				"s": "MTA.LIRR.122",
				"d": "01:33"
			},
			{
				"s": "MTA.LIRR.119",
				"d": "01:35"
			},
			{
				"s": "MTA.LIRR.102",
				"d": "01:43"
			},
			{
				"s": "MTA.LIRR.214",
				"d": "01:51"
			},
			{
				"s": "MTA.LIRR.237",
				"d": "02:02"
			}
		]
	},
	{
		"id": "MTA.LIRR.GO201_26_2704.Weekday",
		"t": "MTA.LIRR.GO201_26_2704",
		"r": "MTA.LIRR.7",
		"n": "2704",
		"y": "MTA.Regional",
		"d": "Outbound",
		"os": [
			"MTA.LIRR.237"
		],
		"tt": [
			{
				"s": "MTA.LIRR.237",
				"d": "02:23"
			},
			{
				"s": "MTA.LIRR.214",
				"d": "02:34"
			},
			{
				"s": "MTA.LIRR.102",
				"d": "02:44"
			},
			{
				"s": "MTA.LIRR.119",
				"d": "02:50"
			},
			{
				"s": "MTA.LIRR.122",
				"d": "02:52"
			},
			{
				"s": "MTA.LIRR.180",
				"d": "02:55"
			},
			{
				"s": "MTA.LIRR.211",
				"d": "02:59"
			},
			{
				"s": "MTA.LIRR.66",
				"d": "03:02"
			},
			{
				"s": "MTA.LIRR.94",
				"d": "03:05"
			},
			{
				"s": "MTA.LIRR.217",
				"d": "03:07"
			},
			{
				"s": "MTA.LIRR.32",
				"d": "03:10"
			},
			{
				"s": "MTA.LIRR.114",
				"d": "03:12"
			},
			{
				"s": "MTA.LIRR.101",
				"d": "03:15"
			},
			{
				"s": "MTA.LIRR.65",
				"d": "03:20"
			}
		]
	},
	{
		"id": "MTA.LIRR.GO201_26_2705.Weekday",
		"t": "MTA.LIRR.GO201_26_2705",
		"r": "MTA.LIRR.7",
		"n": "2705",
		"y": "MTA.Regional",
		"d": "Inbound",
		"os": [
			"MTA.LIRR.65"
		],
		"tt": [
			{
				"s": "MTA.LIRR.65",
				"d": "03:01"
			},
			{
				"s": "MTA.LIRR.101",
				"d": "03:06"
			},
			{
				"s": "MTA.LIRR.114",
				"d": "03:08"
			},
			{
				"s": "MTA.LIRR.32",
				"d": "03:10"
			},
			{
				"s": "MTA.LIRR.217",
				"d": "03:13"
			},
			{
				"s": "MTA.LIRR.94",
				"d": "03:15"
			},
			{
				"s": "MTA.LIRR.66",
				"d": "03:18"
			},
			{
				"s": "MTA.LIRR.211",
				"d": "03:22"
			},
			{
				"s": "MTA.LIRR.180",
				"d": "03:25"
			},
			{
				"s": "MTA.LIRR.122",
				"d": "03:28"
			},
			{
				"s": "MTA.LIRR.119",
				"d": "03:30"
			},
			{
				"s": "MTA.LIRR.102",
				"d": "03:38"
			},
			{
				"s": "MTA.LIRR.107",
				"d": "03:42"
			},
			{
				"s": "MTA.LIRR.55",
				"d": "03:44"
			},
			{
				"s": "MTA.LIRR.214",
				"d": "03:49"
			},
			{
				"s": "MTA.LIRR.237",
				"d": "03:59"
			}
		]
	},
	{
		"id": "MTA.LIRR.GO201_26_2706.Weekday",
		"t": "MTA.LIRR.GO201_26_2706",
		"r": "MTA.LIRR.7",
		"n": "2706",
		"y": "MTA.Regional",
		"d": "Outbound",
		"os": [
			"MTA.LIRR.237"
		],
		"tt": [
			{
				"s": "MTA.LIRR.237",
				"d": "04:23"
			},
			{
				"s": "MTA.LIRR.214",
				"d": "04:34"
			},
			{
				"s": "MTA.LIRR.102",
				"d": "04:44"
			},
			{
				"s": "MTA.LIRR.119",
				"d": "04:50"
			},
			{
				"s": "MTA.LIRR.122",
				"d": "04:52"
			},
			{
				"s": "MTA.LIRR.180",
				"d": "04:55"
			},
			{
				"s": "MTA.LIRR.211",
				"d": "04:58"
			},
			{
				"s": "MTA.LIRR.66",
				"d": "05:02"
			},
			{
				"s": "MTA.LIRR.94",
				"d": "05:05"
			},
			{
				"s": "MTA.LIRR.217",
				"d": "05:07"
			},
			{
				"s": "MTA.LIRR.32",
				"d": "05:10"
			},
			{
				"s": "MTA.LIRR.114",
				"d": "05:12"
			},
			{
				"s": "MTA.LIRR.101",
				"d": "05:15"
			},
			{
				"s": "MTA.LIRR.65",
				"d": "05:20"
			}
		]
	},
	{
		"id": "MTA.LIRR.GO201_26_2710.Weekday",
		"t": "MTA.LIRR.GO201_26_2710",
		"r": "MTA.LIRR.7",
		"n": "2710",
		"y": "MTA.Regional",
		"d": "Outbound",
		"os": [
			"MTA.LIRR.237"
		],
		"tt": [
			{
				"s": "MTA.LIRR.237",
				"d": "04:45"
			},
			{
				"s": "MTA.LIRR.214",
				"d": "04:56"
			},
			{
				"s": "MTA.LIRR.102",
				"d": "05:06"
			},
			{
				"s": "MTA.LIRR.119",
				"d": "05:12"
			},
			{
				"s": "MTA.LIRR.122",
				"d": "05:14"
			},
			{
				"s": "MTA.LIRR.180",
				"d": "05:17"
			},
			{
				"s": "MTA.LIRR.211",
				"d": "05:20"
			},
			{
				"s": "MTA.LIRR.66",
				"d": "05:24"
			},
			{
				"s": "MTA.LIRR.94",
				"d": "05:27"
			},
			{
				"s": "MTA.LIRR.217",
				"d": "05:29"
			},
			{
				"s": "MTA.LIRR.32",
				"d": "05:32"
			},
			{
				"s": "MTA.LIRR.114",
				"d": "05:34"
			},
			{
				"s": "MTA.LIRR.101",
				"d": "05:37"
			},
			{
				"s": "MTA.LIRR.65",
				"d": "05:42"
			}
		]
	},
	{
		"id": "MTA.LIRR.GO201_26_2711.Weekday",
		"t": "MTA.LIRR.GO201_26_2711",
		"r": "MTA.LIRR.7",
		"n": "2711",
		"y": "MTA.Regional",
		"d": "Inbound",
		"os": [
			"MTA.LIRR.65"
		],
		"tt": [
			{
				"s": "MTA.LIRR.65",
				"d": "05:27"
			},
			{
				"s": "MTA.LIRR.101",
				"d": "05:32"
			},
			{
				"s": "MTA.LIRR.114",
				"d": "05:34"
			},
			{
				"s": "MTA.LIRR.32",
				"d": "05:36"
			},
			{
				"s": "MTA.LIRR.217",
				"d": "05:39"
			},
			{
				"s": "MTA.LIRR.94",
				"d": "05:41"
			},
			{
				"s": "MTA.LIRR.66",
				"d": "05:44"
			},
			{
				"s": "MTA.LIRR.211",
				"d": "05:48"
			},
			{
				"s": "MTA.LIRR.180",
				"d": "05:51"
			},
			{
				"s": "MTA.LIRR.122",
				"d": "05:54"
			},
			{
				"s": "MTA.LIRR.119",
				"d": "05:56"
			},
			{
				"s": "MTA.LIRR.102",
				"d": "06:03"
			},
			{
				"s": "MTA.LIRR.50",
				"d": "06:11"
			},
			{
				"s": "MTA.LIRR.148",
				"d": "06:16"
			},
			{
				"s": "MTA.LIRR.241",
				"d": "06:23"
			}
		]
	},
	{
		"id": "MTA.LIRR.GO201_26_2712.Weekday",
		"t": "MTA.LIRR.GO201_26_2712",
		"r": "MTA.LIRR.7",
		"n": "2712",
		"y": "MTA.Regional",
		"d": "Outbound",
		"os": [
			"MTA.LIRR.349"
		],
		"tt": [
			{
				"s": "MTA.LIRR.349",
				"d": "06:29"
			},
			{
				"s": "MTA.LIRR.214",
				"d": "06:41"
			},
			{
				"s": "MTA.LIRR.102",
				"d": "06:51"
			},
			{
				"s": "MTA.LIRR.119",
				"d": "06:57"
			},
			{
				"s": "MTA.LIRR.122",
				"d": "06:59"
			},
			{
				"s": "MTA.LIRR.180",
				"d": "07:02"
			},
			{
				"s": "MTA.LIRR.211",
				"d": "07:05"
			},
			{
				"s": "MTA.LIRR.66",
				"d": "07:09"
			},
			{
				"s": "MTA.LIRR.94",
				"d": "07:12"
			},
			{
				"s": "MTA.LIRR.217",
				"d": "07:14"
			},
			{
				"s": "MTA.LIRR.32",
				"d": "07:17"
			},
			{
				"s": "MTA.LIRR.114",
				"d": "07:19"
			},
			{
				"s": "MTA.LIRR.101",
				"d": "07:22"
			},
			{
				"s": "MTA.LIRR.65",
				"d": "07:27"
			}
		]
	},
	{
		"id": "MTA.LIRR.GO201_26_2713.Weekday",
		"t": "MTA.LIRR.GO201_26_2713",
		"r": "MTA.LIRR.7",
		"n": "2713",
		"y": "MTA.Regional",
		"d": "Inbound",
		"os": [
			"MTA.LIRR.65"
		],
		"tt": [
			{
				"s": "MTA.LIRR.65",
				"d": "05:44"
			},
			{
				"s": "MTA.LIRR.101",
				"d": "05:49"
			},
			{
				"s": "MTA.LIRR.114",
				"d": "05:51"
			},
			{
				"s": "MTA.LIRR.32",
				"d": "05:53"
			},
			{
				"s": "MTA.LIRR.217",
				"d": "05:56"
			},
			{
				"s": "MTA.LIRR.94",
				"d": "05:58"
			},
			{
				"s": "MTA.LIRR.66",
				"d": "06:01"
			},
			{
				"s": "MTA.LIRR.211",
				"d": "06:05"
			},
			{
				"s": "MTA.LIRR.180",
				"d": "06:08"
			},
			{
				"s": "MTA.LIRR.122",
				"d": "06:11"
			},
			{
				"s": "MTA.LIRR.119",
				"d": "06:13"
			},
			{
				"s": "MTA.LIRR.102",
				"d": "06:21"
			},
			{
				"s": "MTA.LIRR.50",
				"d": "06:29"
			},
			{
				"s": "MTA.LIRR.148",
				"d": "06:34"
			},
			{
				"s": "MTA.LIRR.241",
				"d": "06:41"
			}
		]
	},
	{
		"id": "MTA.LIRR.GO201_26_2715.Weekday",
		"t": "MTA.LIRR.GO201_26_2715",
		"r": "MTA.LIRR.7",
		"n": "2715",
		"y": "MTA.Regional",
		"d": "Inbound",
		"os": [
			"MTA.LIRR.65"
		],
		"tt": [
			{
				"s": "MTA.LIRR.65",
				"d": "06:04"
			},
			{
				"s": "MTA.LIRR.101",
				"d": "06:09"
			},
			{
				"s": "MTA.LIRR.114",
				"d": "06:11"
			},
			{
				"s": "MTA.LIRR.32",
				"d": "06:13"
			},
			{
				"s": "MTA.LIRR.217",
				"d": "06:16"
			},
			{
				"s": "MTA.LIRR.94",
				"d": "06:18"
			},
			{
				"s": "MTA.LIRR.66",
				"d": "06:21"
			},
			{
				"s": "MTA.LIRR.211",
				"d": "06:25"
			},
			{
				"s": "MTA.LIRR.122",
				"d": "06:30"
			},
			{
				"s": "MTA.LIRR.119",
				"d": "06:32"
			},
			{
				"s": "MTA.LIRR.102",
				"d": "06:40"
			},
			{
				"s": "MTA.LIRR.349",
				"d": "06:59"
			}
		]
	},
	{
		"id": "MTA.LIRR.GO201_26_2716.Weekday",
		"t": "MTA.LIRR.GO201_26_2716",
		"r": "MTA.LIRR.7",
		"n": "2716",
		"y": "MTA.Regional",
		"d": "Outbound",
		"os": [
			"MTA.LIRR.349"
		],
		"tt": [
			{
				"s": "MTA.LIRR.349",
				"d": "07:28"
			},
			{
				"s": "MTA.LIRR.102",
				"d": "07:50"
			},
			{
				"s": "MTA.LIRR.119",
				"d": "07:56"
			},
			{
				"s": "MTA.LIRR.122",
				"d": "07:58"
			},
			{
				"s": "MTA.LIRR.180",
				"d": "08:01"
			},
			{
				"s": "MTA.LIRR.211",
				"d": "08:04"
			},
			{
				"s": "MTA.LIRR.66",
				"d": "08:08"
			},
			{
				"s": "MTA.LIRR.94",
				"d": "08:11"
			},
			{
				"s": "MTA.LIRR.217",
				"d": "08:13"
			},
			{
				"s": "MTA.LIRR.32",
				"d": "08:16"
			},
			{
				"s": "MTA.LIRR.114",
				"d": "08:18"
			},
			{
				"s": "MTA.LIRR.101",
				"d": "08:21"
			},
			{
				"s": "MTA.LIRR.65",
				"d": "08:26"
			}
		]
	},
	{
		"id": "MTA.LIRR.GO201_26_2717.Weekday",
		"t": "MTA.LIRR.GO201_26_2717",
		"r": "MTA.LIRR.7",
		"n": "2717",
		"y": "MTA.Regional",
		"d": "Inbound",
		"os": [
			"MTA.LIRR.65"
		],
		"tt": [
			{
				"s": "MTA.LIRR.65",
				"d": "06:25"
			},
			{
				"s": "MTA.LIRR.101",
				"d": "06:30"
			},
			{
				"s": "MTA.LIRR.114",
				"d": "06:32"
			},
			{
				"s": "MTA.LIRR.32",
				"d": "06:34"
			},
			{
				"s": "MTA.LIRR.217",
				"d": "06:37"
			},
			{
				"s": "MTA.LIRR.94",
				"d": "06:39"
			},
			{
				"s": "MTA.LIRR.66",
				"d": "06:42"
			},
			{
				"s": "MTA.LIRR.211",
				"d": "06:46"
			},
			{
				"s": "MTA.LIRR.180",
				"d": "06:49"
			},
			{
				"s": "MTA.LIRR.122",
				"d": "06:52"
			},
			{
				"s": "MTA.LIRR.119",
				"d": "06:54"
			},
			{
				"s": "MTA.LIRR.102",
				"d": "07:02"
			},
			{
				"s": "MTA.LIRR.50",
				"d": "07:10"
			},
			{
				"s": "MTA.LIRR.148",
				"d": "07:15"
			},
			{
				"s": "MTA.LIRR.241",
				"d": "07:22"
			}
		]
	},
	{
		"id": "MTA.LIRR.GO201_26_2718.Weekday",
		"t": "MTA.LIRR.GO201_26_2718",
		"r": "MTA.LIRR.7",
		"n": "2718",
		"y": "MTA.Regional",
		"d": "Outbound",
		"os": [
			"MTA.LIRR.349"
		],
		"tt": [
			{
				"s": "MTA.LIRR.349",
				"d": "08:23"
			},
			{
				"s": "MTA.LIRR.214",
				"d": "08:35"
			},
			{
				"s": "MTA.LIRR.102",
				"d": "08:45"
			},
			{
				"s": "MTA.LIRR.119",
				"d": "08:51"
			},
			{
				"s": "MTA.LIRR.122",
				"d": "08:53"
			},
			{
				"s": "MTA.LIRR.180",
				"d": "08:56"
			},
			{
				"s": "MTA.LIRR.211",
				"d": "08:59"
			},
			{
				"s": "MTA.LIRR.66",
				"d": "09:03"
			},
			{
				"s": "MTA.LIRR.94",
				"d": "09:06"
			},
			{
				"s": "MTA.LIRR.217",
				"d": "09:08"
			},
			{
				"s": "MTA.LIRR.32",
				"d": "09:11"
			},
			{
				"s": "MTA.LIRR.114",
				"d": "09:13"
			},
			{
				"s": "MTA.LIRR.101",
				"d": "09:16"
			},
			{
				"s": "MTA.LIRR.65",
				"d": "09:21"
			}
		]
	},
	{
		"id": "MTA.LIRR.GO201_26_2719.Weekday",
		"t": "MTA.LIRR.GO201_26_2719",
		"r": "MTA.LIRR.7",
		"n": "2719",
		"y": "MTA.Regional",
		"d": "Inbound",
		"os": [
			"MTA.LIRR.65"
		],
		"tt": [
			{
				"s": "MTA.LIRR.65",
				"d": "06:47"
			},
			{
				"s": "MTA.LIRR.101",
				"d": "06:52"
			},
			{
				"s": "MTA.LIRR.114",
				"d": "06:54"
			},
			{
				"s": "MTA.LIRR.32",
				"d": "06:56"
			},
			{
				"s": "MTA.LIRR.217",
				"d": "06:59"
			},
			{
				"s": "MTA.LIRR.94",
				"d": "07:01"
			},
			{
				"s": "MTA.LIRR.66",
				"d": "07:04"
			},
			{
				"s": "MTA.LIRR.211",
				"d": "07:08"
			},
			{
				"s": "MTA.LIRR.180",
				"d": "07:11"
			},
			{
				"s": "MTA.LIRR.122",
				"d": "07:14"
			},
			{
				"s": "MTA.LIRR.119",
				"d": "07:16"
			},
			{
				"s": "MTA.LIRR.102",
				"d": "07:24"
			},
			{
				"s": "MTA.LIRR.349",
				"d": "07:43"
			}
		]
	},
	{
		"id": "MTA.LIRR.GO201_26_2720.Weekday",
		"t": "MTA.LIRR.GO201_26_2720",
		"r": "MTA.LIRR.7",
		"n": "2720",
		"y": "MTA.Regional",
		"d": "Outbound",
		"os": [
			"MTA.LIRR.349"
		],
		"tt": [
			{
				"s": "MTA.LIRR.349",
				"d": "09:22"
			},
			{
				"s": "MTA.LIRR.214",
				"d": "09:33"
			},
			{
				"s": "MTA.LIRR.102",
				"d": "09:45"
			},
			{
				"s": "MTA.LIRR.119",
				"d": "09:51"
			},
			{
				"s": "MTA.LIRR.122",
				"d": "09:53"
			},
			{
				"s": "MTA.LIRR.180",
				"d": "09:56"
			},
			{
				"s": "MTA.LIRR.211",
				"d": "09:59"
			},
			{
				"s": "MTA.LIRR.66",
				"d": "10:02"
			},
			{
				"s": "MTA.LIRR.94",
				"d": "10:06"
			},
			{
				"s": "MTA.LIRR.217",
				"d": "10:08"
			},
			{
				"s": "MTA.LIRR.32",
				"d": "10:11"
			},
			{
				"s": "MTA.LIRR.114",
				"d": "10:13"
			},
			{
				"s": "MTA.LIRR.101",
				"d": "10:16"
			},
			{
				"s": "MTA.LIRR.65",
				"d": "10:21"
			}
		]
	},
	{
		"id": "MTA.LIRR.GO201_26_2721.Weekday",
		"t": "MTA.LIRR.GO201_26_2721",
		"r": "MTA.LIRR.7",
		"n": "2721",
		"y": "MTA.Regional",
		"d": "Inbound",
		"os": [
			"MTA.LIRR.65"
		],
		"tt": [
			{
				"s": "MTA.LIRR.65",
				"d": "07:10"
			},
			{
				"s": "MTA.LIRR.101",
				"d": "07:15"
			},
			{
				"s": "MTA.LIRR.114",
				"d": "07:17"
			},
			{
				"s": "MTA.LIRR.32",
				"d": "07:19"
			},
			{
				"s": "MTA.LIRR.217",
				"d": "07:22"
			},
			{
				"s": "MTA.LIRR.94",
				"d": "07:24"
			},
			{
				"s": "MTA.LIRR.66",
				"d": "07:27"
			},
			{
				"s": "MTA.LIRR.211",
				"d": "07:31"
			},
			{
				"s": "MTA.LIRR.180",
				"d": "07:34"
			},
			{
				"s": "MTA.LIRR.122",
				"d": "07:37"
			},
			{
				"s": "MTA.LIRR.119",
				"d": "07:39"
			},
			{
				"s": "MTA.LIRR.102",
				"d": "07:48"
			},
			{
				"s": "MTA.LIRR.237",
				"d": "08:08"
			}
		]
	},
	{
		"id": "MTA.LIRR.GO201_26_2722.Weekday",
		"t": "MTA.LIRR.GO201_26_2722",
		"r": "MTA.LIRR.7",
		"n": "2722",
		"y": "MTA.Regional",
		"d": "Outbound",
		"os": [
			"MTA.LIRR.349"
		],
		"tt": [
			{
				"s": "MTA.LIRR.349",
				"d": "10:13"
			},
			{
				"s": "MTA.LIRR.214",
				"d": "10:24"
			},
			{
				"s": "MTA.LIRR.102",
				"d": "10:36"
			},
			{
				"s": "MTA.LIRR.119",
				"d": "10:42"
			},
			{
				"s": "MTA.LIRR.122",
				"d": "10:44"
			},
			{
				"s": "MTA.LIRR.180",
				"d": "10:47"
			},
			{
				"s": "MTA.LIRR.211",
				"d": "10:50"
			},
			{
				"s": "MTA.LIRR.66",
				"d": "10:54"
			},
			{
				"s": "MTA.LIRR.94",
				"d": "10:57"
			},
			{
				"s": "MTA.LIRR.217",
				"d": "10:59"
			},
			{
				"s": "MTA.LIRR.32",
				"d": "11:02"
			},
			{
				"s": "MTA.LIRR.114",
				"d": "11:04"
			},
			{
				"s": "MTA.LIRR.101",
				"d": "11:07"
			},
			{
				"s": "MTA.LIRR.65",
				"d": "11:12"
			}
		]
	},
	{
		"id": "MTA.LIRR.GO201_26_2723.Weekday",
		"t": "MTA.LIRR.GO201_26_2723",
		"r": "MTA.LIRR.7",
		"n": "2723",
		"y": "MTA.Regional",
		"d": "Inbound",
		"os": [
			"MTA.LIRR.65"
		],
		"tt": [
			{
				"s": "MTA.LIRR.65",
				"d": "07:33"
			},
			{
				"s": "MTA.LIRR.101",
				"d": "07:38"
			},
			{
				"s": "MTA.LIRR.114",
				"d": "07:40"
			},
			{
				"s": "MTA.LIRR.32",
				"d": "07:42"
			},
			{
				"s": "MTA.LIRR.217",
				"d": "07:45"
			},
			{
				"s": "MTA.LIRR.94",
				"d": "07:47"
			},
			{
				"s": "MTA.LIRR.66",
				"d": "07:50"
			},
			{
				"s": "MTA.LIRR.211",
				"d": "07:54"
			},
			{
				"s": "MTA.LIRR.180",
				"d": "07:57"
			},
			{
				"s": "MTA.LIRR.122",
				"d": "08:00"
			},
			{
				"s": "MTA.LIRR.119",
				"d": "08:02"
			},
			{
				"s": "MTA.LIRR.102",
				"d": "08:10"
			},
			{
				"s": "MTA.LIRR.50",
				"d": "08:18"
			},
			{
				"s": "MTA.LIRR.148",
				"d": "08:23"
			},
			{
				"s": "MTA.LIRR.241",
				"d": "08:30"
			}
		]
	},
	{
		"id": "MTA.LIRR.GO201_26_2724.Weekday",
		"t": "MTA.LIRR.GO201_26_2724",
		"r": "MTA.LIRR.7",
		"n": "2724",
		"y": "MTA.Regional",
		"d": "Outbound",
		"os": [
			"MTA.LIRR.349"
		],
		"tt": [
			{
				"s": "MTA.LIRR.349",
				"d": "11:13"
			},
			{
				"s": "MTA.LIRR.214",
				"d": "11:24"
			},
			{
				"s": "MTA.LIRR.102",
				"d": "11:36"
			},
			{
				"s": "MTA.LIRR.119",
				"d": "11:42"
			},
			{
				"s": "MTA.LIRR.122",
				"d": "11:44"
			},
			{
				"s": "MTA.LIRR.180",
				"d": "11:47"
			},
			{
				"s": "MTA.LIRR.211",
				"d": "11:50"
			},
			{
				"s": "MTA.LIRR.66",
				"d": "11:54"
			},
			{
				"s": "MTA.LIRR.94",
				"d": "11:57"
			},
			{
				"s": "MTA.LIRR.217",
				"d": "11:59"
			},
			{
				"s": "MTA.LIRR.32",
				"d": "12:02"
			},
			{
				"s": "MTA.LIRR.114",
				"d": "12:04"
			},
			{
				"s": "MTA.LIRR.101",
				"d": "12:07"
			},
			{
				"s": "MTA.LIRR.65",
				"d": "12:12"
			}
		]
	},
	{
		"id": "MTA.LIRR.GO201_26_2725.Weekday",
		"t": "MTA.LIRR.GO201_26_2725",
		"r": "MTA.LIRR.7",
		"n": "2725",
		"y": "MTA.Regional",
		"d": "Inbound",
		"os": [
			"MTA.LIRR.65"
		],
		"tt": [
			{
				"s": "MTA.LIRR.65",
				"d": "07:50"
			},
			{
				"s": "MTA.LIRR.101",
				"d": "07:55"
			},
			{
				"s": "MTA.LIRR.114",
				"d": "07:57"
			},
			{
				"s": "MTA.LIRR.32",
				"d": "07:59"
			},
			{
				"s": "MTA.LIRR.217",
				"d": "08:02"
			},
			{
				"s": "MTA.LIRR.94",
				"d": "08:04"
			},
			{
				"s": "MTA.LIRR.66",
				"d": "08:07"
			},
			{
				"s": "MTA.LIRR.211",
				"d": "08:11"
			},
			{
				"s": "MTA.LIRR.102",
				"d": "08:25"
			},
			{
				"s": "MTA.LIRR.237",
				"d": "08:43"
			}
		]
	},
	{
		"id": "MTA.LIRR.GO201_26_2727.Weekday",
		"t": "MTA.LIRR.GO201_26_2727",
		"r": "MTA.LIRR.7",
		"n": "2727",
		"y": "MTA.Regional",
		"d": "Inbound",
		"os": [
			"MTA.LIRR.65"
		],
		"tt": [
			{
				"s": "MTA.LIRR.65",
				"d": "08:10"
			},
			{
				"s": "MTA.LIRR.101",
				"d": "08:15"
			},
			{
				"s": "MTA.LIRR.114",
				"d": "08:17"
			},
			{
				"s": "MTA.LIRR.32",
				"d": "08:19"
			},
			{
				"s": "MTA.LIRR.217",
				"d": "08:22"
			},
			{
				"s": "MTA.LIRR.94",
				"d": "08:24"
			},
			{
				"s": "MTA.LIRR.66",
				"d": "08:27"
			},
			{
				"s": "MTA.LIRR.211",
				"d": "08:31"
			},
			{
				"s": "MTA.LIRR.180",
				"d": "08:34"
			},
			{
				"s": "MTA.LIRR.122",
				"d": "08:37"
			},
			{
				"s": "MTA.LIRR.119",
				"d": "08:39"
			},
			{
				"s": "MTA.LIRR.102",
				"d": "08:48"
			},
			{
				"s": "MTA.LIRR.107",
				"d": "08:52"
			},
			{
				"s": "MTA.LIRR.349",
				"d": "09:06"
			}
		]
	},
	{
		"id": "MTA.LIRR.GO201_26_2729.Weekday",
		"t": "MTA.LIRR.GO201_26_2729",
		"r": "MTA.LIRR.7",
		"n": "2729",
		"y": "MTA.Regional",
		"d": "Inbound",
		"os": [
			"MTA.LIRR.65"
		],
		"tt": [
			{
				"s": "MTA.LIRR.65",
				"d": "08:35"
			},
			{
				"s": "MTA.LIRR.101",
				"d": "08:40"
			},
			{
				"s": "MTA.LIRR.114",
				"d": "08:42"
			},
			{
				"s": "MTA.LIRR.32",
				"d": "08:44"
			},
			{
				"s": "MTA.LIRR.217",
				"d": "08:47"
			},
			{
				"s": "MTA.LIRR.94",
				"d": "08:49"
			},
			{
				"s": "MTA.LIRR.66",
				"d": "08:52"
			},
			{
				"s": "MTA.LIRR.211",
				"d": "08:56"
			},
			{
				"s": "MTA.LIRR.180",
				"d": "08:59"
			},
			{
				"s": "MTA.LIRR.122",
				"d": "09:02"
			},
			{
				"s": "MTA.LIRR.119",
				"d": "09:04"
			},
			{
				"s": "MTA.LIRR.102",
				"d": "09:12"
			},
			{
				"s": "MTA.LIRR.214",
				"d": "09:20"
			},
			{
				"s": "MTA.LIRR.237",
				"d": "09:31"
			}
		]
	},
	{
		"id": "MTA.LIRR.GO201_26_2731.Weekday",
		"t": "MTA.LIRR.GO201_26_2731",
		"r": "MTA.LIRR.7",
		"n": "2731",
		"y": "MTA.Regional",
		"d": "Inbound",
		"os": [
			"MTA.LIRR.65"
		],
		"tt": [
			{
				"s": "MTA.LIRR.65",
				"d": "08:53"
			},
			{
				"s": "MTA.LIRR.101",
				"d": "08:58"
			},
			{
				"s": "MTA.LIRR.114",
				"d": "09:00"
			},
			{
				"s": "MTA.LIRR.32",
				"d": "09:02"
			},
			{
				"s": "MTA.LIRR.217",
				"d": "09:05"
			},
			{
				"s": "MTA.LIRR.94",
				"d": "09:07"
			},
			{
				"s": "MTA.LIRR.66",
				"d": "09:10"
			},
			{
				"s": "MTA.LIRR.211",
				"d": "09:14"
			},
			{
				"s": "MTA.LIRR.180",
				"d": "09:17"
			},
			{
				"s": "MTA.LIRR.122",
				"d": "09:20"
			},
			{
				"s": "MTA.LIRR.119",
				"d": "09:22"
			},
			{
				"s": "MTA.LIRR.102",
				"d": "09:30"
			},
			{
				"s": "MTA.LIRR.55",
				"d": "09:35"
			},
			{
				"s": "MTA.LIRR.349",
				"d": "09:49"
			}
		]
	},
	{
		"id": "MTA.LIRR.GO201_26_2733.Weekday",
		"t": "MTA.LIRR.GO201_26_2733",
		"r": "MTA.LIRR.7",
		"n": "2733",
		"y": "MTA.Regional",
		"d": "Inbound",
		"os": [
			"MTA.LIRR.65"
		],
		"tt": [
			{
				"s": "MTA.LIRR.65",
				"d": "09:06"
			},
			{
				"s": "MTA.LIRR.101",
				"d": "09:11"
			},
			{
				"s": "MTA.LIRR.114",
				"d": "09:13"
			},
			{
				"s": "MTA.LIRR.32",
				"d": "09:15"
			},
			{
				"s": "MTA.LIRR.217",
				"d": "09:18"
			},
			{
				"s": "MTA.LIRR.94",
				"d": "09:20"
			},
			{
				"s": "MTA.LIRR.66",
				"d": "09:23"
			},
			{
				"s": "MTA.LIRR.211",
				"d": "09:27"
			},
			{
				"s": "MTA.LIRR.180",
				"d": "09:30"
			},
			{
				"s": "MTA.LIRR.122",
				"d": "09:33"
			},
			{
				"s": "MTA.LIRR.119",
				"d": "09:35"
			},
			{
				"s": "MTA.LIRR.102",
				"d": "09:43"
			},
			{
				"s": "MTA.LIRR.107",
				"d": "09:47"
			},
			{
				"s": "MTA.LIRR.349",
				"d": "10:02"
			}
		]
	},
	{
		"id": "MTA.LIRR.GO201_26_2735.Weekday",
		"t": "MTA.LIRR.GO201_26_2735",
		"r": "MTA.LIRR.7",
		"n": "2735",
		"y": "MTA.Regional",
		"d": "Inbound",
		"os": [
			"MTA.LIRR.65"
		],
		"tt": [
			{
				"s": "MTA.LIRR.65",
				"d": "09:50"
			},
			{
				"s": "MTA.LIRR.101",
				"d": "09:55"
			},
			{
				"s": "MTA.LIRR.114",
				"d": "09:57"
			},
			{
				"s": "MTA.LIRR.32",
				"d": "09:59"
			},
			{
				"s": "MTA.LIRR.217",
				"d": "10:02"
			},
			{
				"s": "MTA.LIRR.94",
				"d": "10:04"
			},
			{
				"s": "MTA.LIRR.66",
				"d": "10:07"
			},
			{
				"s": "MTA.LIRR.211",
				"d": "10:11"
			},
			{
				"s": "MTA.LIRR.180",
				"d": "10:14"
			},
			{
				"s": "MTA.LIRR.122",
				"d": "10:17"
			},
			{
				"s": "MTA.LIRR.119",
				"d": "10:19"
			},
			{
				"s": "MTA.LIRR.102",
				"d": "10:27"
			},
			{
				"s": "MTA.LIRR.349",
				"d": "10:47"
			}
		]
	},
	{
		"id": "MTA.LIRR.GO201_26_2737.Weekday",
		"t": "MTA.LIRR.GO201_26_2737",
		"r": "MTA.LIRR.7",
		"n": "2737",
		"y": "MTA.Regional",
		"d": "Inbound",
		"os": [
			"MTA.LIRR.65"
		],
		"tt": [
			{
				"s": "MTA.LIRR.65",
				"d": "10:50"
			},
			{
				"s": "MTA.LIRR.101",
				"d": "10:55"
			},
			{
				"s": "MTA.LIRR.114",
				"d": "10:57"
			},
			{
				"s": "MTA.LIRR.32",
				"d": "10:59"
			},
			{
				"s": "MTA.LIRR.217",
				"d": "11:02"
			},
			{
				"s": "MTA.LIRR.94",
				"d": "11:04"
			},
			{
				"s": "MTA.LIRR.66",
				"d": "11:07"
			},
			{
				"s": "MTA.LIRR.211",
				"d": "11:11"
			},
			{
				"s": "MTA.LIRR.180",
				"d": "11:14"
			},
			{
				"s": "MTA.LIRR.122",
				"d": "11:17"
			},
			{
				"s": "MTA.LIRR.119",
				"d": "11:19"
			},
			{
				"s": "MTA.LIRR.102",
				"d": "11:27"
			},
			{
				"s": "MTA.LIRR.349",
				"d": "11:47"
			}
		]
	},
	{
		"id": "MTA.LIRR.GO201_26_2739.Weekday",
		"t": "MTA.LIRR.GO201_26_2739",
		"r": "MTA.LIRR.7",
		"n": "2739",
		"y": "MTA.Regional",
		"d": "Inbound",
		"os": [
			"MTA.LIRR.65"
		],
		"tt": [
			{
				"s": "MTA.LIRR.65",
				"d": "11:50"
			},
			{
				"s": "MTA.LIRR.101",
				"d": "11:55"
			},
			{
				"s": "MTA.LIRR.114",
				"d": "11:57"
			},
			{
				"s": "MTA.LIRR.32",
				"d": "11:59"
			},
			{
				"s": "MTA.LIRR.217",
				"d": "12:02"
			},
			{
				"s": "MTA.LIRR.94",
				"d": "12:04"
			},
			{
				"s": "MTA.LIRR.66",
				"d": "12:07"
			},
			{
				"s": "MTA.LIRR.211",
				"d": "12:11"
			},
			{
				"s": "MTA.LIRR.180",
				"d": "12:14"
			},
			{
				"s": "MTA.LIRR.122",
				"d": "12:17"
			},
			{
				"s": "MTA.LIRR.119",
				"d": "12:19"
			},
			{
				"s": "MTA.LIRR.102",
				"d": "12:27"
			},
			{
				"s": "MTA.LIRR.349",
				"d": "12:47"
			}
		]
	},
	{
		"id": "MTA.LIRR.GO201_26_2750.Weekday",
		"t": "MTA.LIRR.GO201_26_2750",
		"r": "MTA.LIRR.7",
		"n": "2750",
		"y": "MTA.Regional",
		"d": "Outbound",
		"os": [
			"MTA.LIRR.349"
		],
		"tt": [
			{
				"s": "MTA.LIRR.349",
				"d": "12:13"
			},
			{
				"s": "MTA.LIRR.214",
				"d": "12:24"
			},
			{
				"s": "MTA.LIRR.102",
				"d": "12:36"
			},
			{
				"s": "MTA.LIRR.119",
				"d": "12:42"
			},
			{
				"s": "MTA.LIRR.122",
				"d": "12:44"
			},
			{
				"s": "MTA.LIRR.180",
				"d": "12:47"
			},
			{
				"s": "MTA.LIRR.211",
				"d": "12:50"
			},
			{
				"s": "MTA.LIRR.66",
				"d": "12:54"
			},
			{
				"s": "MTA.LIRR.94",
				"d": "12:57"
			},
			{
				"s": "MTA.LIRR.217",
				"d": "12:59"
			},
			{
				"s": "MTA.LIRR.32",
				"d": "13:02"
			},
			{
				"s": "MTA.LIRR.114",
				"d": "13:04"
			},
			{
				"s": "MTA.LIRR.101",
				"d": "13:07"
			},
			{
				"s": "MTA.LIRR.65",
				"d": "13:12"
			}
		]
	},
	{
		"id": "MTA.LIRR.GO201_26_2752.Weekday",
		"t": "MTA.LIRR.GO201_26_2752",
		"r": "MTA.LIRR.7",
		"n": "2752",
		"y": "MTA.Regional",
		"d": "Outbound",
		"os": [
			"MTA.LIRR.349"
		],
		"tt": [
			{
				"s": "MTA.LIRR.349",
				"d": "13:17"
			},
			{
				"s": "MTA.LIRR.214",
				"d": "13:28"
			},
			{
				"s": "MTA.LIRR.102",
				"d": "13:39"
			},
			{
				"s": "MTA.LIRR.119",
				"d": "13:45"
			},
			{
				"s": "MTA.LIRR.122",
				"d": "13:47"
			},
			{
				"s": "MTA.LIRR.180",
				"d": "13:50"
			},
			{
				"s": "MTA.LIRR.211",
				"d": "13:53"
			},
			{
				"s": "MTA.LIRR.66",
				"d": "13:57"
			},
			{
				"s": "MTA.LIRR.94",
				"d": "14:00"
			},
			{
				"s": "MTA.LIRR.217",
				"d": "14:02"
			},
			{
				"s": "MTA.LIRR.32",
				"d": "14:05"
			},
			{
				"s": "MTA.LIRR.114",
				"d": "14:07"
			},
			{
				"s": "MTA.LIRR.101",
				"d": "14:10"
			},
			{
				"s": "MTA.LIRR.65",
				"d": "14:15"
			}
		]
	},
	{
		"id": "MTA.LIRR.GO201_26_2753.Weekday",
		"t": "MTA.LIRR.GO201_26_2753",
		"r": "MTA.LIRR.7",
		"n": "2753",
		"y": "MTA.Regional",
		"d": "Inbound",
		"os": [
			"MTA.LIRR.65"
		],
		"tt": [
			{
				"s": "MTA.LIRR.65",
				"d": "12:50"
			},
			{
				"s": "MTA.LIRR.101",
				"d": "12:55"
			},
			{
				"s": "MTA.LIRR.114",
				"d": "12:57"
			},
			{
				"s": "MTA.LIRR.32",
				"d": "12:59"
			},
			{
				"s": "MTA.LIRR.217",
				"d": "13:02"
			},
			{
				"s": "MTA.LIRR.94",
				"d": "13:04"
			},
			{
				"s": "MTA.LIRR.66",
				"d": "13:07"
			},
			{
				"s": "MTA.LIRR.211",
				"d": "13:11"
			},
			{
				"s": "MTA.LIRR.180",
				"d": "13:14"
			},
			{
				"s": "MTA.LIRR.122",
				"d": "13:17"
			},
			{
				"s": "MTA.LIRR.119",
				"d": "13:19"
			},
			{
				"s": "MTA.LIRR.102",
				"d": "13:27"
			},
			{
				"s": "MTA.LIRR.349",
				"d": "13:47"
			}
		]
	},
	{
		"id": "MTA.LIRR.GO201_26_2754.Weekday",
		"t": "MTA.LIRR.GO201_26_2754",
		"r": "MTA.LIRR.7",
		"n": "2754",
		"y": "MTA.Regional",
		"d": "Outbound",
		"os": [
			"MTA.LIRR.349"
		],
		"tt": [
			{
				"s": "MTA.LIRR.349",
				"d": "14:13"
			},
			{
				"s": "MTA.LIRR.214",
				"d": "14:24"
			},
			{
				"s": "MTA.LIRR.102",
				"d": "14:36"
			},
			{
				"s": "MTA.LIRR.119",
				"d": "14:42"
			},
			{
				"s": "MTA.LIRR.122",
				"d": "14:44"
			},
			{
				"s": "MTA.LIRR.180",
				"d": "14:47"
			},
			{
				"s": "MTA.LIRR.211",
				"d": "14:50"
			},
			{
				"s": "MTA.LIRR.66",
				"d": "14:54"
			},
			{
				"s": "MTA.LIRR.94",
				"d": "14:57"
			},
			{
				"s": "MTA.LIRR.217",
				"d": "14:59"
			},
			{
				"s": "MTA.LIRR.32",
				"d": "15:02"
			},
			{
				"s": "MTA.LIRR.114",
				"d": "15:04"
			},
			{
				"s": "MTA.LIRR.101",
				"d": "15:07"
			},
			{
				"s": "MTA.LIRR.65",
				"d": "15:12"
			}
		]
	},
	{
		"id": "MTA.LIRR.GO201_26_2755.Weekday",
		"t": "MTA.LIRR.GO201_26_2755",
		"r": "MTA.LIRR.7",
		"n": "2755",
		"y": "MTA.Regional",
		"d": "Inbound",
		"os": [
			"MTA.LIRR.65"
		],
		"tt": [
			{
				"s": "MTA.LIRR.65",
				"d": "13:50"
			},
			{
				"s": "MTA.LIRR.101",
				"d": "13:55"
			},
			{
				"s": "MTA.LIRR.114",
				"d": "13:57"
			},
			{
				"s": "MTA.LIRR.32",
				"d": "13:59"
			},
			{
				"s": "MTA.LIRR.217",
				"d": "14:02"
			},
			{
				"s": "MTA.LIRR.94",
				"d": "14:04"
			},
			{
				"s": "MTA.LIRR.66",
				"d": "14:07"
			},
			{
				"s": "MTA.LIRR.211",
				"d": "14:11"
			},
			{
				"s": "MTA.LIRR.180",
				"d": "14:14"
			},
			{
				"s": "MTA.LIRR.122",
				"d": "14:17"
			},
			{
				"s": "MTA.LIRR.119",
				"d": "14:19"
			},
			{
				"s": "MTA.LIRR.102",
				"d": "14:27"
			},
			{
				"s": "MTA.LIRR.349",
				"d": "14:47"
			}
		]
	},
	{
		"id": "MTA.LIRR.GO201_26_2756.Weekday",
		"t": "MTA.LIRR.GO201_26_2756",
		"r": "MTA.LIRR.7",
		"n": "2756",
		"y": "MTA.Regional",
		"d": "Outbound",
		"os": [
			"MTA.LIRR.237"
		],
		"tt": [
			{
				"s": "MTA.LIRR.237",
				"d": "14:57"
			},
			{
				"s": "MTA.LIRR.102",
				"d": "15:19"
			},
			{
				"s": "MTA.LIRR.119",
				"d": "15:25"
			},
			{
				"s": "MTA.LIRR.122",
				"d": "15:27"
			},
			{
				"s": "MTA.LIRR.180",
				"d": "15:30"
			},
			{
				"s": "MTA.LIRR.211",
				"d": "15:33"
			},
			{
				"s": "MTA.LIRR.66",
				"d": "15:37"
			},
			{
				"s": "MTA.LIRR.94",
				"d": "15:40"
			},
			{
				"s": "MTA.LIRR.217",
				"d": "15:42"
			},
			{
				"s": "MTA.LIRR.32",
				"d": "15:45"
			},
			{
				"s": "MTA.LIRR.114",
				"d": "15:47"
			},
			{
				"s": "MTA.LIRR.101",
				"d": "15:50"
			},
			{
				"s": "MTA.LIRR.65",
				"d": "15:55"
			}
		]
	},
	{
		"id": "MTA.LIRR.GO201_26_2757.Weekday",
		"t": "MTA.LIRR.GO201_26_2757",
		"r": "MTA.LIRR.7",
		"n": "2757",
		"y": "MTA.Regional",
		"d": "Inbound",
		"os": [
			"MTA.LIRR.65"
		],
		"tt": [
			{
				"s": "MTA.LIRR.65",
				"d": "14:24"
			},
			{
				"s": "MTA.LIRR.101",
				"d": "14:29"
			},
			{
				"s": "MTA.LIRR.114",
				"d": "14:31"
			},
			{
				"s": "MTA.LIRR.32",
				"d": "14:33"
			},
			{
				"s": "MTA.LIRR.217",
				"d": "14:36"
			},
			{
				"s": "MTA.LIRR.94",
				"d": "14:38"
			},
			{
				"s": "MTA.LIRR.66",
				"d": "14:41"
			},
			{
				"s": "MTA.LIRR.211",
				"d": "14:45"
			},
			{
				"s": "MTA.LIRR.180",
				"d": "14:48"
			},
			{
				"s": "MTA.LIRR.122",
				"d": "14:51"
			},
			{
				"s": "MTA.LIRR.119",
				"d": "14:53"
			},
			{
				"s": "MTA.LIRR.102",
				"d": "15:02"
			},
			{
				"s": "MTA.LIRR.214",
				"d": "15:10"
			},
			{
				"s": "MTA.LIRR.349",
				"d": "15:21"
			}
		]
	},
	{
		"id": "MTA.LIRR.GO201_26_2758.Weekday",
		"t": "MTA.LIRR.GO201_26_2758",
		"r": "MTA.LIRR.7",
		"n": "2758",
		"y": "MTA.Regional",
		"d": "Outbound",
		"os": [
			"MTA.LIRR.349"
		],
		"tt": [
			{
				"s": "MTA.LIRR.349",
				"d": "15:22"
			},
			{
				"s": "MTA.LIRR.102",
				"d": "15:44"
			},
			{
				"s": "MTA.LIRR.119",
				"d": "15:50"
			},
			{
				"s": "MTA.LIRR.122",
				"d": "15:52"
			},
			{
				"s": "MTA.LIRR.180",
				"d": "15:55"
			},
			{
				"s": "MTA.LIRR.211",
				"d": "15:58"
			},
			{
				"s": "MTA.LIRR.66",
				"d": "16:02"
			},
			{
				"s": "MTA.LIRR.94",
				"d": "16:05"
			},
			{
				"s": "MTA.LIRR.217",
				"d": "16:07"
			},
			{
				"s": "MTA.LIRR.32",
				"d": "16:10"
			},
			{
				"s": "MTA.LIRR.114",
				"d": "16:12"
			},
			{
				"s": "MTA.LIRR.101",
				"d": "16:15"
			},
			{
				"s": "MTA.LIRR.65",
				"d": "16:20"
			}
		]
	},
	{
		"id": "MTA.LIRR.GO201_26_2759.Weekday",
		"t": "MTA.LIRR.GO201_26_2759",
		"r": "MTA.LIRR.7",
		"n": "2759",
		"y": "MTA.Regional",
		"d": "Inbound",
		"os": [
			"MTA.LIRR.65"
		],
		"tt": [
			{
				"s": "MTA.LIRR.65",
				"d": "15:24"
			},
			{
				"s": "MTA.LIRR.101",
				"d": "15:29"
			},
			{
				"s": "MTA.LIRR.114",
				"d": "15:31"
			},
			{
				"s": "MTA.LIRR.32",
				"d": "15:33"
			},
			{
				"s": "MTA.LIRR.217",
				"d": "15:36"
			},
			{
				"s": "MTA.LIRR.94",
				"d": "15:38"
			},
			{
				"s": "MTA.LIRR.66",
				"d": "15:41"
			},
			{
				"s": "MTA.LIRR.211",
				"d": "15:45"
			},
			{
				"s": "MTA.LIRR.180",
				"d": "15:48"
			},
			{
				"s": "MTA.LIRR.122",
				"d": "15:51"
			},
			{
				"s": "MTA.LIRR.119",
				"d": "15:53"
			},
			{
				"s": "MTA.LIRR.102",
				"d": "16:01"
			},
			{
				"s": "MTA.LIRR.214",
				"d": "16:09"
			},
			{
				"s": "MTA.LIRR.349",
				"d": "16:20"
			}
		]
	},
	{
		"id": "MTA.LIRR.GO201_26_2760.Weekday",
		"t": "MTA.LIRR.GO201_26_2760",
		"r": "MTA.LIRR.7",
		"n": "2760",
		"y": "MTA.Regional",
		"d": "Outbound",
		"os": [
			"MTA.LIRR.349"
		],
		"tt": [
			{
				"s": "MTA.LIRR.349",
				"d": "16:18"
			},
			{
				"s": "MTA.LIRR.214",
				"d": "16:30"
			},
			{
				"s": "MTA.LIRR.107",
				"d": "16:35"
			},
			{
				"s": "MTA.LIRR.102",
				"d": "16:40"
			},
			{
				"s": "MTA.LIRR.119",
				"d": "16:45"
			},
			{
				"s": "MTA.LIRR.122",
				"d": "16:47"
			},
			{
				"s": "MTA.LIRR.180",
				"d": "16:50"
			},
			{
				"s": "MTA.LIRR.211",
				"d": "16:53"
			},
			{
				"s": "MTA.LIRR.66",
				"d": "16:57"
			},
			{
				"s": "MTA.LIRR.94",
				"d": "17:00"
			},
			{
				"s": "MTA.LIRR.217",
				"d": "17:02"
			},
			{
				"s": "MTA.LIRR.32",
				"d": "17:05"
			},
			{
				"s": "MTA.LIRR.114",
				"d": "17:07"
			},
			{
				"s": "MTA.LIRR.101",
				"d": "17:10"
			},
			{
				"s": "MTA.LIRR.65",
				"d": "17:15"
			}
		]
	},
	{
		"id": "MTA.LIRR.GO201_26_2761.Weekday",
		"t": "MTA.LIRR.GO201_26_2761",
		"r": "MTA.LIRR.7",
		"n": "2761",
		"y": "MTA.Regional",
		"d": "Inbound",
		"os": [
			"MTA.LIRR.65"
		],
		"tt": [
			{
				"s": "MTA.LIRR.65",
				"d": "16:06"
			},
			{
				"s": "MTA.LIRR.101",
				"d": "16:11"
			},
			{
				"s": "MTA.LIRR.114",
				"d": "16:13"
			},
			{
				"s": "MTA.LIRR.32",
				"d": "16:15"
			},
			{
				"s": "MTA.LIRR.217",
				"d": "16:18"
			},
			{
				"s": "MTA.LIRR.94",
				"d": "16:20"
			},
			{
				"s": "MTA.LIRR.66",
				"d": "16:23"
			},
			{
				"s": "MTA.LIRR.211",
				"d": "16:27"
			},
			{
				"s": "MTA.LIRR.180",
				"d": "16:30"
			},
			{
				"s": "MTA.LIRR.122",
				"d": "16:33"
			},
			{
				"s": "MTA.LIRR.119",
				"d": "16:35"
			},
			{
				"s": "MTA.LIRR.102",
				"d": "16:43"
			},
			{
				"s": "MTA.LIRR.214",
				"d": "16:52"
			},
			{
				"s": "MTA.LIRR.349",
				"d": "17:02"
			}
		]
	},
	{
		"id": "MTA.LIRR.GO201_26_2762.Weekday",
		"t": "MTA.LIRR.GO201_26_2762",
		"r": "MTA.LIRR.7",
		"n": "2762",
		"y": "MTA.Regional",
		"d": "Outbound",
		"os": [
			"MTA.LIRR.241"
		],
		"tt": [
			{
				"s": "MTA.LIRR.241",
				"d": "16:46"
			},
			{
				"s": "MTA.LIRR.102",
				"d": "17:06"
			},
			{
				"s": "MTA.LIRR.211",
				"d": "17:17"
			},
			{
				"s": "MTA.LIRR.66",
				"d": "17:21"
			},
			{
				"s": "MTA.LIRR.94",
				"d": "17:24"
			},
			{
				"s": "MTA.LIRR.217",
				"d": "17:26"
			},
			{
				"s": "MTA.LIRR.32",
				"d": "17:29"
			},
			{
				"s": "MTA.LIRR.114",
				"d": "17:31"
			},
			{
				"s": "MTA.LIRR.101",
				"d": "17:34"
			},
			{
				"s": "MTA.LIRR.65",
				"d": "17:39"
			}
		]
	},
	{
		"id": "MTA.LIRR.GO201_26_2763.Weekday",
		"t": "MTA.LIRR.GO201_26_2763",
		"r": "MTA.LIRR.7",
		"n": "2763",
		"y": "MTA.Regional",
		"d": "Inbound",
		"os": [
			"MTA.LIRR.65"
		],
		"tt": [
			{
				"s": "MTA.LIRR.65",
				"d": "16:36"
			},
			{
				"s": "MTA.LIRR.101",
				"d": "16:41"
			},
			{
				"s": "MTA.LIRR.114",
				"d": "16:43"
			},
			{
				"s": "MTA.LIRR.32",
				"d": "16:45"
			},
			{
				"s": "MTA.LIRR.217",
				"d": "16:48"
			},
			{
				"s": "MTA.LIRR.94",
				"d": "16:50"
			},
			{
				"s": "MTA.LIRR.66",
				"d": "16:53"
			},
			{
				"s": "MTA.LIRR.211",
				"d": "16:57"
			},
			{
				"s": "MTA.LIRR.180",
				"d": "17:00"
			},
			{
				"s": "MTA.LIRR.122",
				"d": "17:03"
			},
			{
				"s": "MTA.LIRR.119",
				"d": "17:05"
			},
			{
				"s": "MTA.LIRR.102",
				"d": "17:13"
			},
			{
				"s": "MTA.LIRR.214",
				"d": "17:22"
			},
			{
				"s": "MTA.LIRR.237",
				"d": "17:33"
			}
		]
	},
	{
		"id": "MTA.LIRR.GO201_26_2765.Weekday",
		"t": "MTA.LIRR.GO201_26_2765",
		"r": "MTA.LIRR.7",
		"n": "2765",
		"y": "MTA.Regional",
		"d": "Inbound",
		"os": [
			"MTA.LIRR.65"
		],
		"tt": [
			{
				"s": "MTA.LIRR.65",
				"d": "17:19"
			},
			{
				"s": "MTA.LIRR.101",
				"d": "17:24"
			},
			{
				"s": "MTA.LIRR.114",
				"d": "17:26"
			},
			{
				"s": "MTA.LIRR.32",
				"d": "17:28"
			},
			{
				"s": "MTA.LIRR.217",
				"d": "17:31"
			},
			{
				"s": "MTA.LIRR.94",
				"d": "17:33"
			},
			{
				"s": "MTA.LIRR.66",
				"d": "17:36"
			},
			{
				"s": "MTA.LIRR.211",
				"d": "17:40"
			},
			{
				"s": "MTA.LIRR.180",
				"d": "17:43"
			},
			{
				"s": "MTA.LIRR.122",
				"d": "17:46"
			},
			{
				"s": "MTA.LIRR.119",
				"d": "17:48"
			},
			{
				"s": "MTA.LIRR.102",
				"d": "17:56"
			},
			{
				"s": "MTA.LIRR.50",
				"d": "18:04"
			},
			{
				"s": "MTA.LIRR.148",
				"d": "18:09"
			},
			{
				"s": "MTA.LIRR.241",
				"d": "18:16"
			}
		]
	},
	{
		"id": "MTA.LIRR.GO201_26_2766.Weekday",
		"t": "MTA.LIRR.GO201_26_2766",
		"r": "MTA.LIRR.7",
		"n": "2766",
		"y": "MTA.Regional",
		"d": "Outbound",
		"os": [
			"MTA.LIRR.349"
		],
		"tt": [
			{
				"s": "MTA.LIRR.349",
				"d": "17:12"
			},
			{
				"s": "MTA.LIRR.102",
				"d": "17:32"
			},
			{
				"s": "MTA.LIRR.119",
				"d": "17:38"
			},
			{
				"s": "MTA.LIRR.122",
				"d": "17:40"
			},
			{
				"s": "MTA.LIRR.180",
				"d": "17:43"
			},
			{
				"s": "MTA.LIRR.211",
				"d": "17:46"
			},
			{
				"s": "MTA.LIRR.66",
				"d": "17:49"
			},
			{
				"s": "MTA.LIRR.94",
				"d": "17:52"
			},
			{
				"s": "MTA.LIRR.217",
				"d": "17:54"
			},
			{
				"s": "MTA.LIRR.32",
				"d": "17:57"
			},
			{
				"s": "MTA.LIRR.114",
				"d": "17:59"
			},
			{
				"s": "MTA.LIRR.101",
				"d": "18:02"
			},
			{
				"s": "MTA.LIRR.65",
				"d": "18:07"
			}
		]
	},
	{
		"id": "MTA.LIRR.GO201_26_2767.Weekday",
		"t": "MTA.LIRR.GO201_26_2767",
		"r": "MTA.LIRR.7",
		"n": "2767",
		"y": "MTA.Regional",
		"d": "Inbound",
		"os": [
			"MTA.LIRR.65"
		],
		"tt": [
			{
				"s": "MTA.LIRR.65",
				"d": "17:51"
			},
			{
				"s": "MTA.LIRR.101",
				"d": "17:56"
			},
			{
				"s": "MTA.LIRR.114",
				"d": "17:58"
			},
			{
				"s": "MTA.LIRR.32",
				"d": "18:00"
			},
			{
				"s": "MTA.LIRR.217",
				"d": "18:03"
			},
			{
				"s": "MTA.LIRR.94",
				"d": "18:06"
			},
			{
				"s": "MTA.LIRR.66",
				"d": "18:08"
			},
			{
				"s": "MTA.LIRR.211",
				"d": "18:13"
			},
			{
				"s": "MTA.LIRR.102",
				"d": "18:24"
			},
			{
				"s": "MTA.LIRR.349",
				"d": "18:43"
			}
		]
	},
	{
		"id": "MTA.LIRR.GO201_26_2768.Weekday",
		"t": "MTA.LIRR.GO201_26_2768",
		"r": "MTA.LIRR.7",
		"n": "2768",
		"y": "MTA.Regional",
		"d": "Outbound",
		"os": [
			"MTA.LIRR.349"
		],
		"tt": [
			{
				"s": "MTA.LIRR.349",
				"d": "17:36"
			},
			{
				"s": "MTA.LIRR.107",
				"d": "17:53"
			},
			{
				"s": "MTA.LIRR.102",
				"d": "17:59"
			},
			{
				"s": "MTA.LIRR.119",
				"d": "18:05"
			},
			{
				"s": "MTA.LIRR.122",
				"d": "18:07"
			},
			{
				"s": "MTA.LIRR.180",
				"d": "18:10"
			},
			{
				"s": "MTA.LIRR.211",
				"d": "18:14"
			},
			{
				"s": "MTA.LIRR.66",
				"d": "18:18"
			},
			{
				"s": "MTA.LIRR.94",
				"d": "18:21"
			},
			{
				"s": "MTA.LIRR.217",
				"d": "18:23"
			},
			{
				"s": "MTA.LIRR.32",
				"d": "18:26"
			},
			{
				"s": "MTA.LIRR.114",
				"d": "18:28"
			},
			{
				"s": "MTA.LIRR.101",
				"d": "18:31"
			},
			{
				"s": "MTA.LIRR.65",
				"d": "18:36"
			}
		]
	},
	{
		"id": "MTA.LIRR.GO201_26_2769.Weekday",
		"t": "MTA.LIRR.GO201_26_2769",
		"r": "MTA.LIRR.7",
		"n": "2769",
		"y": "MTA.Regional",
		"d": "Inbound",
		"os": [
			"MTA.LIRR.65"
		],
		"tt": [
			{
				"s": "MTA.LIRR.65",
				"d": "18:10"
			},
			{
				"s": "MTA.LIRR.101",
				"d": "18:15"
			},
			{
				"s": "MTA.LIRR.114",
				"d": "18:17"
			},
			{
				"s": "MTA.LIRR.32",
				"d": "18:19"
			},
			{
				"s": "MTA.LIRR.217",
				"d": "18:22"
			},
			{
				"s": "MTA.LIRR.94",
				"d": "18:25"
			},
			{
				"s": "MTA.LIRR.66",
				"d": "18:28"
			},
			{
				"s": "MTA.LIRR.211",
				"d": "18:32"
			},
			{
				"s": "MTA.LIRR.180",
				"d": "18:35"
			},
			{
				"s": "MTA.LIRR.122",
				"d": "18:38"
			},
			{
				"s": "MTA.LIRR.119",
				"d": "18:40"
			},
			{
				"s": "MTA.LIRR.102",
				"d": "18:48"
			},
			{
				"s": "MTA.LIRR.349",
				"d": "19:07"
			}
		]
	},
	{
		"id": "MTA.LIRR.GO201_26_2770.Weekday",
		"t": "MTA.LIRR.GO201_26_2770",
		"r": "MTA.LIRR.7",
		"n": "2770",
		"y": "MTA.Regional",
		"d": "Outbound",
		"os": [
			"MTA.LIRR.349"
		],
		"tt": [
			{
				"s": "MTA.LIRR.349",
				"d": "17:57"
			},
			{
				"s": "MTA.LIRR.55",
				"d": "18:12"
			},
			{
				"s": "MTA.LIRR.102",
				"d": "18:18"
			},
			{
				"s": "MTA.LIRR.119",
				"d": "18:24"
			},
			{
				"s": "MTA.LIRR.122",
				"d": "18:26"
			},
			{
				"s": "MTA.LIRR.180",
				"d": "18:29"
			},
			{
				"s": "MTA.LIRR.211",
				"d": "18:32"
			},
			{
				"s": "MTA.LIRR.66",
				"d": "18:35"
			},
			{
				"s": "MTA.LIRR.94",
				"d": "18:38"
			},
			{
				"s": "MTA.LIRR.217",
				"d": "18:40"
			},
			{
				"s": "MTA.LIRR.32",
				"d": "18:43"
			},
			{
				"s": "MTA.LIRR.114",
				"d": "18:45"
			},
			{
				"s": "MTA.LIRR.101",
				"d": "18:48"
			},
			{
				"s": "MTA.LIRR.65",
				"d": "18:53"
			}
		]
	},
	{
		"id": "MTA.LIRR.GO201_26_2771.Weekday",
		"t": "MTA.LIRR.GO201_26_2771",
		"r": "MTA.LIRR.7",
		"n": "2771",
		"y": "MTA.Regional",
		"d": "Inbound",
		"os": [
			"MTA.LIRR.65"
		],
		"tt": [
			{
				"s": "MTA.LIRR.65",
				"d": "19:20"
			},
			{
				"s": "MTA.LIRR.101",
				"d": "19:25"
			},
			{
				"s": "MTA.LIRR.114",
				"d": "19:28"
			},
			{
				"s": "MTA.LIRR.32",
				"d": "19:30"
			},
			{
				"s": "MTA.LIRR.217",
				"d": "19:33"
			},
			{
				"s": "MTA.LIRR.94",
				"d": "19:35"
			},
			{
				"s": "MTA.LIRR.66",
				"d": "19:38"
			},
			{
				"s": "MTA.LIRR.211",
				"d": "19:42"
			},
			{
				"s": "MTA.LIRR.180",
				"d": "19:45"
			},
			{
				"s": "MTA.LIRR.122",
				"d": "19:48"
			},
			{
				"s": "MTA.LIRR.119",
				"d": "19:50"
			},
			{
				"s": "MTA.LIRR.102",
				"d": "19:59"
			},
			{
				"s": "MTA.LIRR.214",
				"d": "20:07"
			},
			{
				"s": "MTA.LIRR.349",
				"d": "20:18"
			}
		]
	},
	{
		"id": "MTA.LIRR.GO201_26_2772.Weekday",
		"t": "MTA.LIRR.GO201_26_2772",
		"r": "MTA.LIRR.7",
		"n": "2772",
		"y": "MTA.Regional",
		"d": "Outbound",
		"os": [
			"MTA.LIRR.237"
		],
		"tt": [
			{
				"s": "MTA.LIRR.237",
				"d": "18:17"
			},
			{
				"s": "MTA.LIRR.102",
				"d": "18:39"
			},
			{
				"s": "MTA.LIRR.119",
				"d": "18:45"
			},
			{
				"s": "MTA.LIRR.122",
				"d": "18:47"
			},
			{
				"s": "MTA.LIRR.180",
				"d": "18:50"
			},
			{
				"s": "MTA.LIRR.211",
				"d": "18:53"
			},
			{
				"s": "MTA.LIRR.66",
				"d": "18:56"
			},
			{
				"s": "MTA.LIRR.94",
				"d": "18:59"
			},
			{
				"s": "MTA.LIRR.217",
				"d": "19:01"
			},
			{
				"s": "MTA.LIRR.32",
				"d": "19:04"
			},
			{
				"s": "MTA.LIRR.114",
				"d": "19:06"
			},
			{
				"s": "MTA.LIRR.101",
				"d": "19:09"
			},
			{
				"s": "MTA.LIRR.65",
				"d": "19:14"
			}
		]
	},
	{
		"id": "MTA.LIRR.GO201_26_2773.Weekday",
		"t": "MTA.LIRR.GO201_26_2773",
		"r": "MTA.LIRR.7",
		"n": "2773",
		"y": "MTA.Regional",
		"d": "Inbound",
		"os": [
			"MTA.LIRR.65"
		],
		"tt": [
			{
				"s": "MTA.LIRR.65",
				"d": "20:03"
			},
			{
				"s": "MTA.LIRR.101",
				"d": "20:08"
			},
			{
				"s": "MTA.LIRR.114",
				"d": "20:10"
			},
			{
				"s": "MTA.LIRR.32",
				"d": "20:12"
			},
			{
				"s": "MTA.LIRR.217",
				"d": "20:15"
			},
			{
				"s": "MTA.LIRR.94",
				"d": "20:18"
			},
			{
				"s": "MTA.LIRR.66",
				"d": "20:20"
			},
			{
				"s": "MTA.LIRR.211",
				"d": "20:24"
			},
			{
				"s": "MTA.LIRR.180",
				"d": "20:27"
			},
			{
				"s": "MTA.LIRR.122",
				"d": "20:30"
			},
			{
				"s": "MTA.LIRR.119",
				"d": "20:32"
			},
			{
				"s": "MTA.LIRR.102",
				"d": "20:40"
			},
			{
				"s": "MTA.LIRR.107",
				"d": "20:44"
			},
			{
				"s": "MTA.LIRR.55",
				"d": "20:46"
			},
			{
				"s": "MTA.LIRR.349",
				"d": "20:59"
			}
		]
	},
	{
		"id": "MTA.LIRR.GO201_26_2774.Weekday",
		"t": "MTA.LIRR.GO201_26_2774",
		"r": "MTA.LIRR.7",
		"n": "2774",
		"y": "MTA.Regional",
		"d": "Outbound",
		"os": [
			"MTA.LIRR.349"
		],
		"tt": [
			{
				"s": "MTA.LIRR.349",
				"d": "18:36"
			},
			{
				"s": "MTA.LIRR.102",
				"d": "18:56"
			},
			{
				"s": "MTA.LIRR.119",
				"d": "19:02"
			},
			{
				"s": "MTA.LIRR.122",
				"d": "19:04"
			},
			{
				"s": "MTA.LIRR.180",
				"d": "19:07"
			},
			{
				"s": "MTA.LIRR.66",
				"d": "19:13"
			},
			{
				"s": "MTA.LIRR.94",
				"d": "19:16"
			},
			{
				"s": "MTA.LIRR.217",
				"d": "19:18"
			},
			{
				"s": "MTA.LIRR.32",
				"d": "19:21"
			},
			{
				"s": "MTA.LIRR.114",
				"d": "19:23"
			},
			{
				"s": "MTA.LIRR.101",
				"d": "19:26"
			},
			{
				"s": "MTA.LIRR.65",
				"d": "19:31"
			}
		]
	},
	{
		"id": "MTA.LIRR.GO201_26_2775.Weekday",
		"t": "MTA.LIRR.GO201_26_2775",
		"r": "MTA.LIRR.7",
		"n": "2775",
		"y": "MTA.Regional",
		"d": "Inbound",
		"os": [
			"MTA.LIRR.65"
		],
		"tt": [
			{
				"s": "MTA.LIRR.65",
				"d": "21:07"
			},
			{
				"s": "MTA.LIRR.101",
				"d": "21:12"
			},
			{
				"s": "MTA.LIRR.114",
				"d": "21:14"
			},
			{
				"s": "MTA.LIRR.32",
				"d": "21:16"
			},
			{
				"s": "MTA.LIRR.217",
				"d": "21:19"
			},
			{
				"s": "MTA.LIRR.94",
				"d": "21:21"
			},
			{
				"s": "MTA.LIRR.66",
				"d": "21:24"
			},
			{
				"s": "MTA.LIRR.211",
				"d": "21:28"
			},
			{
				"s": "MTA.LIRR.180",
				"d": "21:31"
			},
			{
				"s": "MTA.LIRR.122",
				"d": "21:34"
			},
			{
				"s": "MTA.LIRR.119",
				"d": "21:36"
			},
			{
				"s": "MTA.LIRR.102",
				"d": "21:45"
			},
			{
				"s": "MTA.LIRR.107",
				"d": "21:49"
			},
			{
				"s": "MTA.LIRR.55",
				"d": "21:51"
			},
			{
				"s": "MTA.LIRR.349",
				"d": "22:05"
			}
		]
	},
	{
		"id": "MTA.LIRR.GO201_26_2776.Weekday",
		"t": "MTA.LIRR.GO201_26_2776",
		"r": "MTA.LIRR.7",
		"n": "2776",
		"y": "MTA.Regional",
		"d": "Outbound",
		"os": [
			"MTA.LIRR.349"
		],
		"tt": [
			{
				"s": "MTA.LIRR.349",
				"d": "18:56"
			},
			{
				"s": "MTA.LIRR.102",
				"d": "19:16"
			},
			{
				"s": "MTA.LIRR.119",
				"d": "19:22"
			},
			{
				"s": "MTA.LIRR.122",
				"d": "19:24"
			},
			{
				"s": "MTA.LIRR.180",
				"d": "19:27"
			},
			{
				"s": "MTA.LIRR.66",
				"d": "19:33"
			},
			{
				"s": "MTA.LIRR.94",
				"d": "19:36"
			},
			{
				"s": "MTA.LIRR.217",
				"d": "19:38"
			},
			{
				"s": "MTA.LIRR.32",
				"d": "19:41"
			},
			{
				"s": "MTA.LIRR.114",
				"d": "19:44"
			},
			{
				"s": "MTA.LIRR.101",
				"d": "19:46"
			},
			{
				"s": "MTA.LIRR.65",
				"d": "19:51"
			}
		]
	},
	{
		"id": "MTA.LIRR.GO201_26_2777.Weekday",
		"t": "MTA.LIRR.GO201_26_2777",
		"r": "MTA.LIRR.7",
		"n": "2777",
		"y": "MTA.Regional",
		"d": "Inbound",
		"os": [
			"MTA.LIRR.65"
		],
		"tt": [
			{
				"s": "MTA.LIRR.65",
				"d": "22:12"
			},
			{
				"s": "MTA.LIRR.101",
				"d": "22:17"
			},
			{
				"s": "MTA.LIRR.114",
				"d": "22:19"
			},
			{
				"s": "MTA.LIRR.32",
				"d": "22:21"
			},
			{
				"s": "MTA.LIRR.217",
				"d": "22:24"
			},
			{
				"s": "MTA.LIRR.94",
				"d": "22:26"
			},
			{
				"s": "MTA.LIRR.66",
				"d": "22:29"
			},
			{
				"s": "MTA.LIRR.211",
				"d": "22:33"
			},
			{
				"s": "MTA.LIRR.180",
				"d": "22:36"
			},
			{
				"s": "MTA.LIRR.122",
				"d": "22:39"
			},
			{
				"s": "MTA.LIRR.119",
				"d": "22:41"
			},
			{
				"s": "MTA.LIRR.102",
				"d": "22:50"
			},
			{
				"s": "MTA.LIRR.214",
				"d": "22:59"
			},
			{
				"s": "MTA.LIRR.349",
				"d": "23:10"
			}
		]
	},
	{
		"id": "MTA.LIRR.GO201_26_2778.Weekday",
		"t": "MTA.LIRR.GO201_26_2778",
		"r": "MTA.LIRR.7",
		"n": "2778",
		"y": "MTA.Regional",
		"d": "Outbound",
		"os": [
			"MTA.LIRR.237"
		],
		"tt": [
			{
				"s": "MTA.LIRR.237",
				"d": "19:26"
			},
			{
				"s": "MTA.LIRR.107",
				"d": "19:42"
			},
			{
				"s": "MTA.LIRR.102",
				"d": "19:46"
			},
			{
				"s": "MTA.LIRR.119",
				"d": "19:52"
			},
			{
				"s": "MTA.LIRR.122",
				"d": "19:54"
			},
			{
				"s": "MTA.LIRR.180",
				"d": "19:57"
			},
			{
				"s": "MTA.LIRR.211",
				"d": "20:00"
			},
			{
				"s": "MTA.LIRR.66",
				"d": "20:04"
			},
			{
				"s": "MTA.LIRR.94",
				"d": "20:07"
			},
			{
				"s": "MTA.LIRR.217",
				"d": "20:09"
			},
			{
				"s": "MTA.LIRR.32",
				"d": "20:12"
			},
			{
				"s": "MTA.LIRR.114",
				"d": "20:14"
			},
			{
				"s": "MTA.LIRR.101",
				"d": "20:17"
			},
			{
				"s": "MTA.LIRR.65",
				"d": "20:22"
			}
		]
	},
	{
		"id": "MTA.LIRR.GO201_26_2779.Weekday",
		"t": "MTA.LIRR.GO201_26_2779",
		"r": "MTA.LIRR.7",
		"n": "2779",
		"y": "MTA.Regional",
		"d": "Inbound",
		"os": [
			"MTA.LIRR.65"
		],
		"tt": [
			{
				"s": "MTA.LIRR.65",
				"d": "23:14"
			},
			{
				"s": "MTA.LIRR.101",
				"d": "23:19"
			},
			{
				"s": "MTA.LIRR.114",
				"d": "23:21"
			},
			{
				"s": "MTA.LIRR.32",
				"d": "23:23"
			},
			{
				"s": "MTA.LIRR.217",
				"d": "23:26"
			},
			{
				"s": "MTA.LIRR.94",
				"d": "23:28"
			},
			{
				"s": "MTA.LIRR.66",
				"d": "23:31"
			},
			{
				"s": "MTA.LIRR.211",
				"d": "23:35"
			},
			{
				"s": "MTA.LIRR.180",
				"d": "23:38"
			},
			{
				"s": "MTA.LIRR.122",
				"d": "23:41"
			},
			{
				"s": "MTA.LIRR.119",
				"d": "23:43"
			},
			{
				"s": "MTA.LIRR.102",
				"d": "23:52"
			},
			{
				"s": "MTA.LIRR.214",
				"d": "24:00"
			},
			{
				"s": "MTA.LIRR.349",
				"d": "24:11"
			}
		]
	},
	{
		"id": "MTA.LIRR.GO201_26_2780.Weekday",
		"t": "MTA.LIRR.GO201_26_2780",
		"r": "MTA.LIRR.7",
		"n": "2780",
		"y": "MTA.Regional",
		"d": "Outbound",
		"os": [
			"MTA.LIRR.349"
		],
		"tt": [
			{
				"s": "MTA.LIRR.349",
				"d": "19:55"
			},
			{
				"s": "MTA.LIRR.214",
				"d": "20:07"
			},
			{
				"s": "MTA.LIRR.102",
				"d": "20:16"
			},
			{
				"s": "MTA.LIRR.119",
				"d": "20:22"
			},
			{
				"s": "MTA.LIRR.122",
				"d": "20:24"
			},
			{
				"s": "MTA.LIRR.180",
				"d": "20:27"
			},
			{
				"s": "MTA.LIRR.211",
				"d": "20:30"
			},
			{
				"s": "MTA.LIRR.66",
				"d": "20:34"
			},
			{
				"s": "MTA.LIRR.94",
				"d": "20:37"
			},
			{
				"s": "MTA.LIRR.217",
				"d": "20:39"
			},
			{
				"s": "MTA.LIRR.32",
				"d": "20:42"
			},
			{
				"s": "MTA.LIRR.114",
				"d": "20:44"
			},
			{
				"s": "MTA.LIRR.101",
				"d": "20:47"
			},
			{
				"s": "MTA.LIRR.65",
				"d": "20:52"
			}
		]
	},
	{
		"id": "MTA.LIRR.GO201_26_2784.Weekday",
		"t": "MTA.LIRR.GO201_26_2784",
		"r": "MTA.LIRR.7",
		"n": "2784",
		"y": "MTA.Regional",
		"d": "Outbound",
		"os": [
			"MTA.LIRR.349"
		],
		"tt": [
			{
				"s": "MTA.LIRR.349",
				"d": "20:24"
			},
			{
				"s": "MTA.LIRR.55",
				"d": "20:39"
			},
			{
				"s": "MTA.LIRR.107",
				"d": "20:41"
			},
			{
				"s": "MTA.LIRR.102",
				"d": "20:47"
			},
			{
				"s": "MTA.LIRR.119",
				"d": "20:53"
			},
			{
				"s": "MTA.LIRR.122",
				"d": "20:55"
			},
			{
				"s": "MTA.LIRR.180",
				"d": "20:58"
			},
			{
				"s": "MTA.LIRR.211",
				"d": "21:01"
			},
			{
				"s": "MTA.LIRR.66",
				"d": "21:05"
			},
			{
				"s": "MTA.LIRR.94",
				"d": "21:08"
			},
			{
				"s": "MTA.LIRR.217",
				"d": "21:10"
			},
			{
				"s": "MTA.LIRR.32",
				"d": "21:13"
			},
			{
				"s": "MTA.LIRR.114",
				"d": "21:15"
			},
			{
				"s": "MTA.LIRR.101",
				"d": "21:18"
			},
			{
				"s": "MTA.LIRR.65",
				"d": "21:23"
			}
		]
	},
	{
		"id": "MTA.LIRR.GO201_26_2786.Weekday",
		"t": "MTA.LIRR.GO201_26_2786",
		"r": "MTA.LIRR.7",
		"n": "2786",
		"y": "MTA.Regional",
		"d": "Outbound",
		"os": [
			"MTA.LIRR.349"
		],
		"tt": [
			{
				"s": "MTA.LIRR.349",
				"d": "21:24"
			},
			{
				"s": "MTA.LIRR.55",
				"d": "21:39"
			},
			{
				"s": "MTA.LIRR.107",
				"d": "21:41"
			},
			{
				"s": "MTA.LIRR.102",
				"d": "21:47"
			},
			{
				"s": "MTA.LIRR.119",
				"d": "21:52"
			},
			{
				"s": "MTA.LIRR.122",
				"d": "21:55"
			},
			{
				"s": "MTA.LIRR.180",
				"d": "21:58"
			},
			{
				"s": "MTA.LIRR.211",
				"d": "22:01"
			},
			{
				"s": "MTA.LIRR.66",
				"d": "22:05"
			},
			{
				"s": "MTA.LIRR.94",
				"d": "22:08"
			},
			{
				"s": "MTA.LIRR.217",
				"d": "22:10"
			},
			{
				"s": "MTA.LIRR.32",
				"d": "22:13"
			},
			{
				"s": "MTA.LIRR.114",
				"d": "22:15"
			},
			{
				"s": "MTA.LIRR.101",
				"d": "22:18"
			},
			{
				"s": "MTA.LIRR.65",
				"d": "22:23"
			}
		]
	},
	{
		"id": "MTA.LIRR.GO201_26_2788.Weekday",
		"t": "MTA.LIRR.GO201_26_2788",
		"r": "MTA.LIRR.7",
		"n": "2788",
		"y": "MTA.Regional",
		"d": "Outbound",
		"os": [
			"MTA.LIRR.349"
		],
		"tt": [
			{
				"s": "MTA.LIRR.349",
				"d": "22:28"
			},
			{
				"s": "MTA.LIRR.55",
				"d": "22:43"
			},
			{
				"s": "MTA.LIRR.107",
				"d": "22:45"
			},
			{
				"s": "MTA.LIRR.102",
				"d": "22:51"
			},
			{
				"s": "MTA.LIRR.119",
				"d": "22:57"
			},
			{
				"s": "MTA.LIRR.122",
				"d": "22:59"
			},
			{
				"s": "MTA.LIRR.180",
				"d": "23:02"
			},
			{
				"s": "MTA.LIRR.211",
				"d": "23:05"
			},
			{
				"s": "MTA.LIRR.66",
				"d": "23:09"
			},
			{
				"s": "MTA.LIRR.94",
				"d": "23:12"
			},
			{
				"s": "MTA.LIRR.217",
				"d": "23:14"
			},
			{
				"s": "MTA.LIRR.32",
				"d": "23:17"
			},
			{
				"s": "MTA.LIRR.114",
				"d": "23:19"
			},
			{
				"s": "MTA.LIRR.101",
				"d": "23:22"
			},
			{
				"s": "MTA.LIRR.65",
				"d": "23:27"
			}
		]
	},
	{
		"id": "MTA.LIRR.GO201_26_2790.Weekday",
		"t": "MTA.LIRR.GO201_26_2790",
		"r": "MTA.LIRR.7",
		"n": "2790",
		"y": "MTA.Regional",
		"d": "Outbound",
		"os": [
			"MTA.LIRR.349"
		],
		"tt": [
			{
				"s": "MTA.LIRR.349",
				"d": "23:30"
			},
			{
				"s": "MTA.LIRR.55",
				"d": "23:45"
			},
			{
				"s": "MTA.LIRR.107",
				"d": "23:47"
			},
			{
				"s": "MTA.LIRR.102",
				"d": "23:53"
			},
			{
				"s": "MTA.LIRR.119",
				"d": "23:59"
			},
			{
				"s": "MTA.LIRR.122",
				"d": "24:01"
			},
			{
				"s": "MTA.LIRR.180",
				"d": "24:04"
			},
			{
				"s": "MTA.LIRR.211",
				"d": "24:07"
			},
			{
				"s": "MTA.LIRR.66",
				"d": "24:11"
			},
			{
				"s": "MTA.LIRR.94",
				"d": "24:14"
			},
			{
				"s": "MTA.LIRR.217",
				"d": "24:16"
			},
			{
				"s": "MTA.LIRR.32",
				"d": "24:19"
			},
			{
				"s": "MTA.LIRR.114",
				"d": "24:21"
			},
			{
				"s": "MTA.LIRR.101",
				"d": "24:24"
			},
			{
				"s": "MTA.LIRR.65",
				"d": "24:29"
			}
		]
	},
	{
		"id": "MTA.LIRR.GO201_26_2797.Weekday",
		"t": "MTA.LIRR.GO201_26_2797",
		"r": "MTA.LIRR.7",
		"n": "2797",
		"y": "MTA.Regional",
		"d": "Inbound",
		"os": [
			"MTA.LIRR.211"
		],
		"tt": [
			{
				"s": "MTA.LIRR.211",
				"d": "07:26"
			},
			{
				"s": "MTA.LIRR.180",
				"d": "07:28"
			},
			{
				"s": "MTA.LIRR.122",
				"d": "07:31"
			},
			{
				"s": "MTA.LIRR.119",
				"d": "07:33"
			},
			{
				"s": "MTA.LIRR.102",
				"d": "07:44"
			},
			{
				"s": "MTA.LIRR.50",
				"d": "07:53"
			},
			{
				"s": "MTA.LIRR.148",
				"d": "07:58"
			},
			{
				"s": "MTA.LIRR.241",
				"d": "08:05"
			}
		]
	},
	{
		"id": "MTA.LIRR.GO201_26_8701.Holiday",
		"t": "MTA.LIRR.GO201_26_8701",
		"r": "MTA.LIRR.7",
		"n": "8701",
		"y": "MTA.Regional",
		"d": "Inbound",
		"os": [
			"MTA.LIRR.65"
		],
		"tt": [
			{
				"s": "MTA.LIRR.65",
				"d": "00:36"
			},
			{
				"s": "MTA.LIRR.101",
				"d": "00:41"
			},
			{
				"s": "MTA.LIRR.114",
				"d": "00:43"
			},
			{
				"s": "MTA.LIRR.32",
				"d": "00:45"
			},
			{
				"s": "MTA.LIRR.217",
				"d": "00:48"
			},
			{
				"s": "MTA.LIRR.94",
				"d": "00:50"
			},
			{
				"s": "MTA.LIRR.66",
				"d": "00:53"
			},
			{
				"s": "MTA.LIRR.211",
				"d": "00:57"
			},
			{
				"s": "MTA.LIRR.180",
				"d": "01:00"
			},
			{
				"s": "MTA.LIRR.122",
				"d": "01:03"
			},
			{
				"s": "MTA.LIRR.119",
				"d": "01:05"
			},
			{
				"s": "MTA.LIRR.102",
				"d": "01:13"
			},
			{
				"s": "MTA.LIRR.214",
				"d": "01:21"
			},
			{
				"s": "MTA.LIRR.349",
				"d": "01:32"
			}
		]
	},
	{
		"id": "MTA.LIRR.GO201_26_8702.Holiday",
		"t": "MTA.LIRR.GO201_26_8702",
		"r": "MTA.LIRR.7",
		"n": "8702",
		"y": "MTA.Regional",
		"d": "Outbound",
		"os": [
			"MTA.LIRR.349"
		],
		"tt": [
			{
				"s": "MTA.LIRR.349",
				"d": "00:37"
			},
			{
				"s": "MTA.LIRR.214",
				"d": "00:48"
			},
			{
				"s": "MTA.LIRR.102",
				"d": "00:59"
			},
			{
				"s": "MTA.LIRR.119",
				"d": "01:04"
			},
			{
				"s": "MTA.LIRR.122",
				"d": "01:06"
			},
			{
				"s": "MTA.LIRR.180",
				"d": "01:09"
			},
			{
				"s": "MTA.LIRR.211",
				"d": "01:12"
			},
			{
				"s": "MTA.LIRR.66",
				"d": "01:16"
			},
			{
				"s": "MTA.LIRR.94",
				"d": "01:19"
			},
			{
				"s": "MTA.LIRR.217",
				"d": "01:21"
			},
			{
				"s": "MTA.LIRR.32",
				"d": "01:24"
			},
			{
				"s": "MTA.LIRR.114",
				"d": "01:26"
			},
			{
				"s": "MTA.LIRR.101",
				"d": "01:29"
			},
			{
				"s": "MTA.LIRR.65",
				"d": "01:34"
			}
		]
	},
	{
		"id": "MTA.LIRR.GO201_26_8703.Holiday",
		"t": "MTA.LIRR.GO201_26_8703",
		"r": "MTA.LIRR.7",
		"n": "8703",
		"y": "MTA.Regional",
		"d": "Inbound",
		"os": [
			"MTA.LIRR.65"
		],
		"tt": [
			{
				"s": "MTA.LIRR.65",
				"d": "01:01"
			},
			{
				"s": "MTA.LIRR.101",
				"d": "01:06"
			},
			{
				"s": "MTA.LIRR.114",
				"d": "01:08"
			},
			{
				"s": "MTA.LIRR.32",
				"d": "01:10"
			},
			{
				"s": "MTA.LIRR.217",
				"d": "01:13"
			},
			{
				"s": "MTA.LIRR.94",
				"d": "01:15"
			},
			{
				"s": "MTA.LIRR.66",
				"d": "01:18"
			},
			{
				"s": "MTA.LIRR.211",
				"d": "01:22"
			},
			{
				"s": "MTA.LIRR.180",
				"d": "01:25"
			},
			{
				"s": "MTA.LIRR.122",
				"d": "01:28"
			},
			{
				"s": "MTA.LIRR.119",
				"d": "01:30"
			},
			{
				"s": "MTA.LIRR.102",
				"d": "01:39"
			},
			{
				"s": "MTA.LIRR.237",
				"d": "01:59"
			}
		]
	},
	{
		"id": "MTA.LIRR.GO201_26_8704.Holiday",
		"t": "MTA.LIRR.GO201_26_8704",
		"r": "MTA.LIRR.7",
		"n": "8704",
		"y": "MTA.Regional",
		"d": "Outbound",
		"os": [
			"MTA.LIRR.237"
		],
		"tt": [
			{
				"s": "MTA.LIRR.237",
				"d": "02:22"
			},
			{
				"s": "MTA.LIRR.55",
				"d": "02:37"
			},
			{
				"s": "MTA.LIRR.107",
				"d": "02:39"
			},
			{
				"s": "MTA.LIRR.102",
				"d": "02:44"
			},
			{
				"s": "MTA.LIRR.119",
				"d": "02:50"
			},
			{
				"s": "MTA.LIRR.122",
				"d": "02:52"
			},
			{
				"s": "MTA.LIRR.180",
				"d": "02:55"
			},
			{
				"s": "MTA.LIRR.211",
				"d": "02:58"
			},
			{
				"s": "MTA.LIRR.66",
				"d": "03:02"
			},
			{
				"s": "MTA.LIRR.94",
				"d": "03:05"
			},
			{
				"s": "MTA.LIRR.217",
				"d": "03:07"
			},
			{
				"s": "MTA.LIRR.32",
				"d": "03:10"
			},
			{
				"s": "MTA.LIRR.114",
				"d": "03:12"
			},
			{
				"s": "MTA.LIRR.101",
				"d": "03:15"
			},
			{
				"s": "MTA.LIRR.65",
				"d": "03:20"
			}
		]
	},
	{
		"id": "MTA.LIRR.GO201_26_8705.Holiday",
		"t": "MTA.LIRR.GO201_26_8705",
		"r": "MTA.LIRR.7",
		"n": "8705",
		"y": "MTA.Regional",
		"d": "Inbound",
		"os": [
			"MTA.LIRR.65"
		],
		"tt": [
			{
				"s": "MTA.LIRR.65",
				"d": "03:05"
			},
			{
				"s": "MTA.LIRR.101",
				"d": "03:10"
			},
			{
				"s": "MTA.LIRR.114",
				"d": "03:12"
			},
			{
				"s": "MTA.LIRR.32",
				"d": "03:14"
			},
			{
				"s": "MTA.LIRR.217",
				"d": "03:17"
			},
			{
				"s": "MTA.LIRR.94",
				"d": "03:19"
			},
			{
				"s": "MTA.LIRR.66",
				"d": "03:22"
			},
			{
				"s": "MTA.LIRR.211",
				"d": "03:26"
			},
			{
				"s": "MTA.LIRR.180",
				"d": "03:29"
			},
			{
				"s": "MTA.LIRR.122",
				"d": "03:32"
			},
			{
				"s": "MTA.LIRR.119",
				"d": "03:34"
			},
			{
				"s": "MTA.LIRR.102",
				"d": "03:42"
			},
			{
				"s": "MTA.LIRR.237",
				"d": "04:00"
			}
		]
	},
	{
		"id": "MTA.LIRR.GO201_26_8706.Holiday",
		"t": "MTA.LIRR.GO201_26_8706",
		"r": "MTA.LIRR.7",
		"n": "8706",
		"y": "MTA.Regional",
		"d": "Outbound",
		"os": [
			"MTA.LIRR.237"
		],
		"tt": [
			{
				"s": "MTA.LIRR.237",
				"d": "04:22"
			},
			{
				"s": "MTA.LIRR.55",
				"d": "04:37"
			},
			{
				"s": "MTA.LIRR.107",
				"d": "04:39"
			},
			{
				"s": "MTA.LIRR.102",
				"d": "04:44"
			},
			{
				"s": "MTA.LIRR.119",
				"d": "04:50"
			},
			{
				"s": "MTA.LIRR.122",
				"d": "04:52"
			},
			{
				"s": "MTA.LIRR.180",
				"d": "04:55"
			},
			{
				"s": "MTA.LIRR.211",
				"d": "04:58"
			},
			{
				"s": "MTA.LIRR.66",
				"d": "05:02"
			},
			{
				"s": "MTA.LIRR.94",
				"d": "05:05"
			},
			{
				"s": "MTA.LIRR.217",
				"d": "05:07"
			},
			{
				"s": "MTA.LIRR.32",
				"d": "05:10"
			},
			{
				"s": "MTA.LIRR.114",
				"d": "05:12"
			},
			{
				"s": "MTA.LIRR.101",
				"d": "05:15"
			},
			{
				"s": "MTA.LIRR.65",
				"d": "05:20"
			}
		]
	},
	{
		"id": "MTA.LIRR.GO201_26_8708.Holiday",
		"t": "MTA.LIRR.GO201_26_8708",
		"r": "MTA.LIRR.7",
		"n": "8708",
		"y": "MTA.Regional",
		"d": "Outbound",
		"os": [
			"MTA.LIRR.349"
		],
		"tt": [
			{
				"s": "MTA.LIRR.349",
				"d": "05:35"
			},
			{
				"s": "MTA.LIRR.214",
				"d": "05:47"
			},
			{
				"s": "MTA.LIRR.102",
				"d": "05:58"
			},
			{
				"s": "MTA.LIRR.119",
				"d": "06:04"
			},
			{
				"s": "MTA.LIRR.122",
				"d": "06:06"
			},
			{
				"s": "MTA.LIRR.180",
				"d": "06:09"
			},
			{
				"s": "MTA.LIRR.211",
				"d": "06:12"
			},
			{
				"s": "MTA.LIRR.66",
				"d": "06:16"
			},
			{
				"s": "MTA.LIRR.94",
				"d": "06:19"
			},
			{
				"s": "MTA.LIRR.217",
				"d": "06:21"
			},
			{
				"s": "MTA.LIRR.32",
				"d": "06:24"
			},
			{
				"s": "MTA.LIRR.114",
				"d": "06:26"
			},
			{
				"s": "MTA.LIRR.101",
				"d": "06:29"
			},
			{
				"s": "MTA.LIRR.65",
				"d": "06:34"
			}
		]
	},
	{
		"id": "MTA.LIRR.GO201_26_8709.Holiday",
		"t": "MTA.LIRR.GO201_26_8709",
		"r": "MTA.LIRR.7",
		"n": "8709",
		"y": "MTA.Regional",
		"d": "Inbound",
		"os": [
			"MTA.LIRR.65"
		],
		"tt": [
			{
				"s": "MTA.LIRR.65",
				"d": "04:59"
			},
			{
				"s": "MTA.LIRR.101",
				"d": "05:04"
			},
			{
				"s": "MTA.LIRR.114",
				"d": "05:06"
			},
			{
				"s": "MTA.LIRR.32",
				"d": "05:08"
			},
			{
				"s": "MTA.LIRR.217",
				"d": "05:11"
			},
			{
				"s": "MTA.LIRR.94",
				"d": "05:13"
			},
			{
				"s": "MTA.LIRR.66",
				"d": "05:16"
			},
			{
				"s": "MTA.LIRR.211",
				"d": "05:20"
			},
			{
				"s": "MTA.LIRR.180",
				"d": "05:23"
			},
			{
				"s": "MTA.LIRR.122",
				"d": "05:26"
			},
			{
				"s": "MTA.LIRR.119",
				"d": "05:28"
			},
			{
				"s": "MTA.LIRR.102",
				"d": "05:36"
			},
			{
				"s": "MTA.LIRR.214",
				"d": "05:45"
			},
			{
				"s": "MTA.LIRR.349",
				"d": "05:56"
			}
		]
	},
	{
		"id": "MTA.LIRR.GO201_26_8710.Holiday",
		"t": "MTA.LIRR.GO201_26_8710",
		"r": "MTA.LIRR.7",
		"n": "8710",
		"y": "MTA.Regional",
		"d": "Outbound",
		"os": [
			"MTA.LIRR.349"
		],
		"tt": [
			{
				"s": "MTA.LIRR.349",
				"d": "06:48"
			},
			{
				"s": "MTA.LIRR.214",
				"d": "07:00"
			},
			{
				"s": "MTA.LIRR.102",
				"d": "07:10"
			},
			{
				"s": "MTA.LIRR.119",
				"d": "07:16"
			},
			{
				"s": "MTA.LIRR.122",
				"d": "07:18"
			},
			{
				"s": "MTA.LIRR.180",
				"d": "07:21"
			},
			{
				"s": "MTA.LIRR.211",
				"d": "07:24"
			},
			{
				"s": "MTA.LIRR.66",
				"d": "07:28"
			},
			{
				"s": "MTA.LIRR.94",
				"d": "07:31"
			},
			{
				"s": "MTA.LIRR.217",
				"d": "07:33"
			},
			{
				"s": "MTA.LIRR.32",
				"d": "07:36"
			},
			{
				"s": "MTA.LIRR.114",
				"d": "07:38"
			},
			{
				"s": "MTA.LIRR.101",
				"d": "07:41"
			},
			{
				"s": "MTA.LIRR.65",
				"d": "07:46"
			}
		]
	},
	{
		"id": "MTA.LIRR.GO201_26_8711.Holiday",
		"t": "MTA.LIRR.GO201_26_8711",
		"r": "MTA.LIRR.7",
		"n": "8711",
		"y": "MTA.Regional",
		"d": "Inbound",
		"os": [
			"MTA.LIRR.65"
		],
		"tt": [
			{
				"s": "MTA.LIRR.65",
				"d": "06:07"
			},
			{
				"s": "MTA.LIRR.101",
				"d": "06:12"
			},
			{
				"s": "MTA.LIRR.114",
				"d": "06:14"
			},
			{
				"s": "MTA.LIRR.32",
				"d": "06:16"
			},
			{
				"s": "MTA.LIRR.217",
				"d": "06:19"
			},
			{
				"s": "MTA.LIRR.94",
				"d": "06:21"
			},
			{
				"s": "MTA.LIRR.66",
				"d": "06:24"
			},
			{
				"s": "MTA.LIRR.211",
				"d": "06:28"
			},
			{
				"s": "MTA.LIRR.180",
				"d": "06:31"
			},
			{
				"s": "MTA.LIRR.122",
				"d": "06:34"
			},
			{
				"s": "MTA.LIRR.119",
				"d": "06:36"
			},
			{
				"s": "MTA.LIRR.102",
				"d": "06:44"
			},
			{
				"s": "MTA.LIRR.214",
				"d": "06:53"
			},
			{
				"s": "MTA.LIRR.349",
				"d": "07:04"
			}
		]
	},
	{
		"id": "MTA.LIRR.GO201_26_8712.Holiday",
		"t": "MTA.LIRR.GO201_26_8712",
		"r": "MTA.LIRR.7",
		"n": "8712",
		"y": "MTA.Regional",
		"d": "Outbound",
		"os": [
			"MTA.LIRR.349"
		],
		"tt": [
			{
				"s": "MTA.LIRR.349",
				"d": "07:39"
			},
			{
				"s": "MTA.LIRR.214",
				"d": "07:51"
			},
			{
				"s": "MTA.LIRR.102",
				"d": "08:01"
			},
			{
				"s": "MTA.LIRR.119",
				"d": "08:07"
			},
			{
				"s": "MTA.LIRR.122",
				"d": "08:09"
			},
			{
				"s": "MTA.LIRR.180",
				"d": "08:12"
			},
			{
				"s": "MTA.LIRR.211",
				"d": "08:15"
			},
			{
				"s": "MTA.LIRR.66",
				"d": "08:19"
			},
			{
				"s": "MTA.LIRR.94",
				"d": "08:22"
			},
			{
				"s": "MTA.LIRR.217",
				"d": "08:24"
			},
			{
				"s": "MTA.LIRR.32",
				"d": "08:27"
			},
			{
				"s": "MTA.LIRR.114",
				"d": "08:29"
			},
			{
				"s": "MTA.LIRR.101",
				"d": "08:32"
			},
			{
				"s": "MTA.LIRR.65",
				"d": "08:37"
			}
		]
	},
	{
		"id": "MTA.LIRR.GO201_26_8713.Holiday",
		"t": "MTA.LIRR.GO201_26_8713",
		"r": "MTA.LIRR.7",
		"n": "8713",
		"y": "MTA.Regional",
		"d": "Inbound",
		"os": [
			"MTA.LIRR.65"
		],
		"tt": [
			{
				"s": "MTA.LIRR.65",
				"d": "07:07"
			},
			{
				"s": "MTA.LIRR.101",
				"d": "07:12"
			},
			{
				"s": "MTA.LIRR.114",
				"d": "07:14"
			},
			{
				"s": "MTA.LIRR.32",
				"d": "07:16"
			},
			{
				"s": "MTA.LIRR.217",
				"d": "07:19"
			},
			{
				"s": "MTA.LIRR.94",
				"d": "07:21"
			},
			{
				"s": "MTA.LIRR.66",
				"d": "07:24"
			},
			{
				"s": "MTA.LIRR.211",
				"d": "07:28"
			},
			{
				"s": "MTA.LIRR.180",
				"d": "07:31"
			},
			{
				"s": "MTA.LIRR.122",
				"d": "07:34"
			},
			{
				"s": "MTA.LIRR.119",
				"d": "07:36"
			},
			{
				"s": "MTA.LIRR.102",
				"d": "07:44"
			},
			{
				"s": "MTA.LIRR.214",
				"d": "07:53"
			},
			{
				"s": "MTA.LIRR.349",
				"d": "08:04"
			}
		]
	},
	{
		"id": "MTA.LIRR.GO201_26_8714.Holiday",
		"t": "MTA.LIRR.GO201_26_8714",
		"r": "MTA.LIRR.7",
		"n": "8714",
		"y": "MTA.Regional",
		"d": "Outbound",
		"os": [
			"MTA.LIRR.349"
		],
		"tt": [
			{
				"s": "MTA.LIRR.349",
				"d": "08:39"
			},
			{
				"s": "MTA.LIRR.214",
				"d": "08:51"
			},
			{
				"s": "MTA.LIRR.102",
				"d": "09:01"
			},
			{
				"s": "MTA.LIRR.119",
				"d": "09:07"
			},
			{
				"s": "MTA.LIRR.122",
				"d": "09:09"
			},
			{
				"s": "MTA.LIRR.180",
				"d": "09:12"
			},
			{
				"s": "MTA.LIRR.211",
				"d": "09:15"
			},
			{
				"s": "MTA.LIRR.66",
				"d": "09:19"
			},
			{
				"s": "MTA.LIRR.94",
				"d": "09:22"
			},
			{
				"s": "MTA.LIRR.217",
				"d": "09:24"
			},
			{
				"s": "MTA.LIRR.32",
				"d": "09:27"
			},
			{
				"s": "MTA.LIRR.114",
				"d": "09:29"
			},
			{
				"s": "MTA.LIRR.101",
				"d": "09:32"
			},
			{
				"s": "MTA.LIRR.65",
				"d": "09:37"
			}
		]
	},
	{
		"id": "MTA.LIRR.GO201_26_8715.Holiday",
		"t": "MTA.LIRR.GO201_26_8715",
		"r": "MTA.LIRR.7",
		"n": "8715",
		"y": "MTA.Regional",
		"d": "Inbound",
		"os": [
			"MTA.LIRR.65"
		],
		"tt": [
			{
				"s": "MTA.LIRR.65",
				"d": "08:11"
			},
			{
				"s": "MTA.LIRR.101",
				"d": "08:16"
			},
			{
				"s": "MTA.LIRR.114",
				"d": "08:18"
			},
			{
				"s": "MTA.LIRR.32",
				"d": "08:20"
			},
			{
				"s": "MTA.LIRR.217",
				"d": "08:23"
			},
			{
				"s": "MTA.LIRR.94",
				"d": "08:25"
			},
			{
				"s": "MTA.LIRR.66",
				"d": "08:28"
			},
			{
				"s": "MTA.LIRR.211",
				"d": "08:32"
			},
			{
				"s": "MTA.LIRR.180",
				"d": "08:35"
			},
			{
				"s": "MTA.LIRR.122",
				"d": "08:38"
			},
			{
				"s": "MTA.LIRR.119",
				"d": "08:40"
			},
			{
				"s": "MTA.LIRR.102",
				"d": "08:48"
			},
			{
				"s": "MTA.LIRR.214",
				"d": "08:57"
			},
			{
				"s": "MTA.LIRR.349",
				"d": "09:08"
			}
		]
	},
	{
		"id": "MTA.LIRR.GO201_26_8716.Holiday",
		"t": "MTA.LIRR.GO201_26_8716",
		"r": "MTA.LIRR.7",
		"n": "8716",
		"y": "MTA.Regional",
		"d": "Outbound",
		"os": [
			"MTA.LIRR.349"
		],
		"tt": [
			{
				"s": "MTA.LIRR.349",
				"d": "09:39"
			},
			{
				"s": "MTA.LIRR.214",
				"d": "09:51"
			},
			{
				"s": "MTA.LIRR.102",
				"d": "10:01"
			},
			{
				"s": "MTA.LIRR.119",
				"d": "10:07"
			},
			{
				"s": "MTA.LIRR.122",
				"d": "10:09"
			},
			{
				"s": "MTA.LIRR.180",
				"d": "10:12"
			},
			{
				"s": "MTA.LIRR.211",
				"d": "10:15"
			},
			{
				"s": "MTA.LIRR.66",
				"d": "10:19"
			},
			{
				"s": "MTA.LIRR.94",
				"d": "10:22"
			},
			{
				"s": "MTA.LIRR.217",
				"d": "10:24"
			},
			{
				"s": "MTA.LIRR.32",
				"d": "10:27"
			},
			{
				"s": "MTA.LIRR.114",
				"d": "10:29"
			},
			{
				"s": "MTA.LIRR.101",
				"d": "10:32"
			},
			{
				"s": "MTA.LIRR.65",
				"d": "10:37"
			}
		]
	},
	{
		"id": "MTA.LIRR.GO201_26_8717.Holiday",
		"t": "MTA.LIRR.GO201_26_8717",
		"r": "MTA.LIRR.7",
		"n": "8717",
		"y": "MTA.Regional",
		"d": "Inbound",
		"os": [
			"MTA.LIRR.65"
		],
		"tt": [
			{
				"s": "MTA.LIRR.65",
				"d": "09:11"
			},
			{
				"s": "MTA.LIRR.101",
				"d": "09:16"
			},
			{
				"s": "MTA.LIRR.114",
				"d": "09:18"
			},
			{
				"s": "MTA.LIRR.32",
				"d": "09:20"
			},
			{
				"s": "MTA.LIRR.217",
				"d": "09:23"
			},
			{
				"s": "MTA.LIRR.94",
				"d": "09:25"
			},
			{
				"s": "MTA.LIRR.66",
				"d": "09:28"
			},
			{
				"s": "MTA.LIRR.211",
				"d": "09:32"
			},
			{
				"s": "MTA.LIRR.180",
				"d": "09:35"
			},
			{
				"s": "MTA.LIRR.122",
				"d": "09:38"
			},
			{
				"s": "MTA.LIRR.119",
				"d": "09:40"
			},
			{
				"s": "MTA.LIRR.102",
				"d": "09:48"
			},
			{
				"s": "MTA.LIRR.214",
				"d": "09:57"
			},
			{
				"s": "MTA.LIRR.349",
				"d": "10:08"
			}
		]
	},
	{
		"id": "MTA.LIRR.GO201_26_8718.Holiday",
		"t": "MTA.LIRR.GO201_26_8718",
		"r": "MTA.LIRR.7",
		"n": "8718",
		"y": "MTA.Regional",
		"d": "Outbound",
		"os": [
			"MTA.LIRR.349"
		],
		"tt": [
			{
				"s": "MTA.LIRR.349",
				"d": "10:39"
			},
			{
				"s": "MTA.LIRR.214",
				"d": "10:51"
			},
			{
				"s": "MTA.LIRR.102",
				"d": "11:01"
			},
			{
				"s": "MTA.LIRR.119",
				"d": "11:07"
			},
			{
				"s": "MTA.LIRR.122",
				"d": "11:09"
			},
			{
				"s": "MTA.LIRR.180",
				"d": "11:12"
			},
			{
				"s": "MTA.LIRR.211",
				"d": "11:15"
			},
			{
				"s": "MTA.LIRR.66",
				"d": "11:19"
			},
			{
				"s": "MTA.LIRR.94",
				"d": "11:22"
			},
			{
				"s": "MTA.LIRR.217",
				"d": "11:24"
			},
			{
				"s": "MTA.LIRR.32",
				"d": "11:27"
			},
			{
				"s": "MTA.LIRR.114",
				"d": "11:29"
			},
			{
				"s": "MTA.LIRR.101",
				"d": "11:32"
			},
			{
				"s": "MTA.LIRR.65",
				"d": "11:37"
			}
		]
	},
	{
		"id": "MTA.LIRR.GO201_26_8719.Holiday",
		"t": "MTA.LIRR.GO201_26_8719",
		"r": "MTA.LIRR.7",
		"n": "8719",
		"y": "MTA.Regional",
		"d": "Inbound",
		"os": [
			"MTA.LIRR.65"
		],
		"tt": [
			{
				"s": "MTA.LIRR.65",
				"d": "10:11"
			},
			{
				"s": "MTA.LIRR.101",
				"d": "10:16"
			},
			{
				"s": "MTA.LIRR.114",
				"d": "10:18"
			},
			{
				"s": "MTA.LIRR.32",
				"d": "10:20"
			},
			{
				"s": "MTA.LIRR.217",
				"d": "10:23"
			},
			{
				"s": "MTA.LIRR.94",
				"d": "10:25"
			},
			{
				"s": "MTA.LIRR.66",
				"d": "10:28"
			},
			{
				"s": "MTA.LIRR.211",
				"d": "10:32"
			},
			{
				"s": "MTA.LIRR.180",
				"d": "10:35"
			},
			{
				"s": "MTA.LIRR.122",
				"d": "10:38"
			},
			{
				"s": "MTA.LIRR.119",
				"d": "10:40"
			},
			{
				"s": "MTA.LIRR.102",
				"d": "10:48"
			},
			{
				"s": "MTA.LIRR.214",
				"d": "10:57"
			},
			{
				"s": "MTA.LIRR.349",
				"d": "11:08"
			}
		]
	},
	{
		"id": "MTA.LIRR.GO201_26_8720.Holiday",
		"t": "MTA.LIRR.GO201_26_8720",
		"r": "MTA.LIRR.7",
		"n": "8720",
		"y": "MTA.Regional",
		"d": "Outbound",
		"os": [
			"MTA.LIRR.349"
		],
		"tt": [
			{
				"s": "MTA.LIRR.349",
				"d": "11:39"
			},
			{
				"s": "MTA.LIRR.214",
				"d": "11:51"
			},
			{
				"s": "MTA.LIRR.102",
				"d": "12:01"
			},
			{
				"s": "MTA.LIRR.119",
				"d": "12:07"
			},
			{
				"s": "MTA.LIRR.122",
				"d": "12:09"
			},
			{
				"s": "MTA.LIRR.180",
				"d": "12:12"
			},
			{
				"s": "MTA.LIRR.211",
				"d": "12:15"
			},
			{
				"s": "MTA.LIRR.66",
				"d": "12:19"
			},
			{
				"s": "MTA.LIRR.94",
				"d": "12:22"
			},
			{
				"s": "MTA.LIRR.217",
				"d": "12:24"
			},
			{
				"s": "MTA.LIRR.32",
				"d": "12:27"
			},
			{
				"s": "MTA.LIRR.114",
				"d": "12:29"
			},
			{
				"s": "MTA.LIRR.101",
				"d": "12:32"
			},
			{
				"s": "MTA.LIRR.65",
				"d": "12:37"
			}
		]
	},
	{
		"id": "MTA.LIRR.GO201_26_8721.Holiday",
		"t": "MTA.LIRR.GO201_26_8721",
		"r": "MTA.LIRR.7",
		"n": "8721",
		"y": "MTA.Regional",
		"d": "Inbound",
		"os": [
			"MTA.LIRR.65"
		],
		"tt": [
			{
				"s": "MTA.LIRR.65",
				"d": "11:11"
			},
			{
				"s": "MTA.LIRR.101",
				"d": "11:16"
			},
			{
				"s": "MTA.LIRR.114",
				"d": "11:18"
			},
			{
				"s": "MTA.LIRR.32",
				"d": "11:20"
			},
			{
				"s": "MTA.LIRR.217",
				"d": "11:23"
			},
			{
				"s": "MTA.LIRR.94",
				"d": "11:25"
			},
			{
				"s": "MTA.LIRR.66",
				"d": "11:28"
			},
			{
				"s": "MTA.LIRR.211",
				"d": "11:32"
			},
			{
				"s": "MTA.LIRR.180",
				"d": "11:35"
			},
			{
				"s": "MTA.LIRR.122",
				"d": "11:38"
			},
			{
				"s": "MTA.LIRR.119",
				"d": "11:40"
			},
			{
				"s": "MTA.LIRR.102",
				"d": "11:48"
			},
			{
				"s": "MTA.LIRR.214",
				"d": "11:57"
			},
			{
				"s": "MTA.LIRR.349",
				"d": "12:08"
			}
		]
	},
	{
		"id": "MTA.LIRR.GO201_26_8750.Holiday",
		"t": "MTA.LIRR.GO201_26_8750",
		"r": "MTA.LIRR.7",
		"n": "8750",
		"y": "MTA.Regional",
		"d": "Outbound",
		"os": [
			"MTA.LIRR.349"
		],
		"tt": [
			{
				"s": "MTA.LIRR.349",
				"d": "12:39"
			},
			{
				"s": "MTA.LIRR.214",
				"d": "12:51"
			},
			{
				"s": "MTA.LIRR.102",
				"d": "13:01"
			},
			{
				"s": "MTA.LIRR.119",
				"d": "13:07"
			},
			{
				"s": "MTA.LIRR.122",
				"d": "13:09"
			},
			{
				"s": "MTA.LIRR.180",
				"d": "13:12"
			},
			{
				"s": "MTA.LIRR.211",
				"d": "13:15"
			},
			{
				"s": "MTA.LIRR.66",
				"d": "13:19"
			},
			{
				"s": "MTA.LIRR.94",
				"d": "13:22"
			},
			{
				"s": "MTA.LIRR.217",
				"d": "13:24"
			},
			{
				"s": "MTA.LIRR.32",
				"d": "13:27"
			},
			{
				"s": "MTA.LIRR.114",
				"d": "13:29"
			},
			{
				"s": "MTA.LIRR.101",
				"d": "13:32"
			},
			{
				"s": "MTA.LIRR.65",
				"d": "13:37"
			}
		]
	},
	{
		"id": "MTA.LIRR.GO201_26_8751.Holiday",
		"t": "MTA.LIRR.GO201_26_8751",
		"r": "MTA.LIRR.7",
		"n": "8751",
		"y": "MTA.Regional",
		"d": "Inbound",
		"os": [
			"MTA.LIRR.65"
		],
		"tt": [
			{
				"s": "MTA.LIRR.65",
				"d": "12:11"
			},
			{
				"s": "MTA.LIRR.101",
				"d": "12:16"
			},
			{
				"s": "MTA.LIRR.114",
				"d": "12:18"
			},
			{
				"s": "MTA.LIRR.32",
				"d": "12:20"
			},
			{
				"s": "MTA.LIRR.217",
				"d": "12:23"
			},
			{
				"s": "MTA.LIRR.94",
				"d": "12:25"
			},
			{
				"s": "MTA.LIRR.66",
				"d": "12:28"
			},
			{
				"s": "MTA.LIRR.211",
				"d": "12:32"
			},
			{
				"s": "MTA.LIRR.180",
				"d": "12:35"
			},
			{
				"s": "MTA.LIRR.122",
				"d": "12:38"
			},
			{
				"s": "MTA.LIRR.119",
				"d": "12:40"
			},
			{
				"s": "MTA.LIRR.102",
				"d": "12:48"
			},
			{
				"s": "MTA.LIRR.214",
				"d": "12:57"
			},
			{
				"s": "MTA.LIRR.349",
				"d": "13:08"
			}
		]
	},
	{
		"id": "MTA.LIRR.GO201_26_8752.Holiday",
		"t": "MTA.LIRR.GO201_26_8752",
		"r": "MTA.LIRR.7",
		"n": "8752",
		"y": "MTA.Regional",
		"d": "Outbound",
		"os": [
			"MTA.LIRR.349"
		],
		"tt": [
			{
				"s": "MTA.LIRR.349",
				"d": "13:39"
			},
			{
				"s": "MTA.LIRR.214",
				"d": "13:51"
			},
			{
				"s": "MTA.LIRR.102",
				"d": "14:01"
			},
			{
				"s": "MTA.LIRR.119",
				"d": "14:07"
			},
			{
				"s": "MTA.LIRR.122",
				"d": "14:09"
			},
			{
				"s": "MTA.LIRR.180",
				"d": "14:12"
			},
			{
				"s": "MTA.LIRR.211",
				"d": "14:15"
			},
			{
				"s": "MTA.LIRR.66",
				"d": "14:19"
			},
			{
				"s": "MTA.LIRR.94",
				"d": "14:22"
			},
			{
				"s": "MTA.LIRR.217",
				"d": "14:24"
			},
			{
				"s": "MTA.LIRR.32",
				"d": "14:27"
			},
			{
				"s": "MTA.LIRR.114",
				"d": "14:29"
			},
			{
				"s": "MTA.LIRR.101",
				"d": "14:32"
			},
			{
				"s": "MTA.LIRR.65",
				"d": "14:37"
			}
		]
	},
	{
		"id": "MTA.LIRR.GO201_26_8753.Holiday",
		"t": "MTA.LIRR.GO201_26_8753",
		"r": "MTA.LIRR.7",
		"n": "8753",
		"y": "MTA.Regional",
		"d": "Inbound",
		"os": [
			"MTA.LIRR.65"
		],
		"tt": [
			{
				"s": "MTA.LIRR.65",
				"d": "13:11"
			},
			{
				"s": "MTA.LIRR.101",
				"d": "13:16"
			},
			{
				"s": "MTA.LIRR.114",
				"d": "13:18"
			},
			{
				"s": "MTA.LIRR.32",
				"d": "13:20"
			},
			{
				"s": "MTA.LIRR.217",
				"d": "13:23"
			},
			{
				"s": "MTA.LIRR.94",
				"d": "13:25"
			},
			{
				"s": "MTA.LIRR.66",
				"d": "13:28"
			},
			{
				"s": "MTA.LIRR.211",
				"d": "13:32"
			},
			{
				"s": "MTA.LIRR.180",
				"d": "13:35"
			},
			{
				"s": "MTA.LIRR.122",
				"d": "13:38"
			},
			{
				"s": "MTA.LIRR.119",
				"d": "13:40"
			},
			{
				"s": "MTA.LIRR.102",
				"d": "13:48"
			},
			{
				"s": "MTA.LIRR.214",
				"d": "13:57"
			},
			{
				"s": "MTA.LIRR.349",
				"d": "14:08"
			}
		]
	},
	{
		"id": "MTA.LIRR.GO201_26_8754.Holiday",
		"t": "MTA.LIRR.GO201_26_8754",
		"r": "MTA.LIRR.7",
		"n": "8754",
		"y": "MTA.Regional",
		"d": "Outbound",
		"os": [
			"MTA.LIRR.349"
		],
		"tt": [
			{
				"s": "MTA.LIRR.349",
				"d": "14:39"
			},
			{
				"s": "MTA.LIRR.214",
				"d": "14:51"
			},
			{
				"s": "MTA.LIRR.102",
				"d": "15:01"
			},
			{
				"s": "MTA.LIRR.119",
				"d": "15:07"
			},
			{
				"s": "MTA.LIRR.122",
				"d": "15:09"
			},
			{
				"s": "MTA.LIRR.180",
				"d": "15:12"
			},
			{
				"s": "MTA.LIRR.211",
				"d": "15:15"
			},
			{
				"s": "MTA.LIRR.66",
				"d": "15:19"
			},
			{
				"s": "MTA.LIRR.94",
				"d": "15:22"
			},
			{
				"s": "MTA.LIRR.217",
				"d": "15:24"
			},
			{
				"s": "MTA.LIRR.32",
				"d": "15:27"
			},
			{
				"s": "MTA.LIRR.114",
				"d": "15:29"
			},
			{
				"s": "MTA.LIRR.101",
				"d": "15:32"
			},
			{
				"s": "MTA.LIRR.65",
				"d": "15:37"
			}
		]
	},
	{
		"id": "MTA.LIRR.GO201_26_8755.Holiday",
		"t": "MTA.LIRR.GO201_26_8755",
		"r": "MTA.LIRR.7",
		"n": "8755",
		"y": "MTA.Regional",
		"d": "Inbound",
		"os": [
			"MTA.LIRR.65"
		],
		"tt": [
			{
				"s": "MTA.LIRR.65",
				"d": "14:11"
			},
			{
				"s": "MTA.LIRR.101",
				"d": "14:16"
			},
			{
				"s": "MTA.LIRR.114",
				"d": "14:18"
			},
			{
				"s": "MTA.LIRR.32",
				"d": "14:20"
			},
			{
				"s": "MTA.LIRR.217",
				"d": "14:23"
			},
			{
				"s": "MTA.LIRR.94",
				"d": "14:25"
			},
			{
				"s": "MTA.LIRR.66",
				"d": "14:28"
			},
			{
				"s": "MTA.LIRR.211",
				"d": "14:32"
			},
			{
				"s": "MTA.LIRR.180",
				"d": "14:35"
			},
			{
				"s": "MTA.LIRR.122",
				"d": "14:38"
			},
			{
				"s": "MTA.LIRR.119",
				"d": "14:40"
			},
			{
				"s": "MTA.LIRR.102",
				"d": "14:48"
			},
			{
				"s": "MTA.LIRR.214",
				"d": "14:57"
			},
			{
				"s": "MTA.LIRR.349",
				"d": "15:08"
			}
		]
	},
	{
		"id": "MTA.LIRR.GO201_26_8756.Holiday",
		"t": "MTA.LIRR.GO201_26_8756",
		"r": "MTA.LIRR.7",
		"n": "8756",
		"y": "MTA.Regional",
		"d": "Outbound",
		"os": [
			"MTA.LIRR.349"
		],
		"tt": [
			{
				"s": "MTA.LIRR.349",
				"d": "15:39"
			},
			{
				"s": "MTA.LIRR.214",
				"d": "15:51"
			},
			{
				"s": "MTA.LIRR.102",
				"d": "16:01"
			},
			{
				"s": "MTA.LIRR.119",
				"d": "16:07"
			},
			{
				"s": "MTA.LIRR.122",
				"d": "16:09"
			},
			{
				"s": "MTA.LIRR.180",
				"d": "16:12"
			},
			{
				"s": "MTA.LIRR.211",
				"d": "16:15"
			},
			{
				"s": "MTA.LIRR.66",
				"d": "16:19"
			},
			{
				"s": "MTA.LIRR.94",
				"d": "16:22"
			},
			{
				"s": "MTA.LIRR.217",
				"d": "16:24"
			},
			{
				"s": "MTA.LIRR.32",
				"d": "16:27"
			},
			{
				"s": "MTA.LIRR.114",
				"d": "16:29"
			},
			{
				"s": "MTA.LIRR.101",
				"d": "16:32"
			},
			{
				"s": "MTA.LIRR.65",
				"d": "16:37"
			}
		]
	},
	{
		"id": "MTA.LIRR.GO201_26_8757.Holiday",
		"t": "MTA.LIRR.GO201_26_8757",
		"r": "MTA.LIRR.7",
		"n": "8757",
		"y": "MTA.Regional",
		"d": "Inbound",
		"os": [
			"MTA.LIRR.65"
		],
		"tt": [
			{
				"s": "MTA.LIRR.65",
				"d": "15:11"
			},
			{
				"s": "MTA.LIRR.101",
				"d": "15:16"
			},
			{
				"s": "MTA.LIRR.114",
				"d": "15:18"
			},
			{
				"s": "MTA.LIRR.32",
				"d": "15:20"
			},
			{
				"s": "MTA.LIRR.217",
				"d": "15:23"
			},
			{
				"s": "MTA.LIRR.94",
				"d": "15:25"
			},
			{
				"s": "MTA.LIRR.66",
				"d": "15:28"
			},
			{
				"s": "MTA.LIRR.211",
				"d": "15:32"
			},
			{
				"s": "MTA.LIRR.180",
				"d": "15:35"
			},
			{
				"s": "MTA.LIRR.122",
				"d": "15:38"
			},
			{
				"s": "MTA.LIRR.119",
				"d": "15:40"
			},
			{
				"s": "MTA.LIRR.102",
				"d": "15:48"
			},
			{
				"s": "MTA.LIRR.214",
				"d": "15:57"
			},
			{
				"s": "MTA.LIRR.349",
				"d": "16:08"
			}
		]
	},
	{
		"id": "MTA.LIRR.GO201_26_8758.Holiday",
		"t": "MTA.LIRR.GO201_26_8758",
		"r": "MTA.LIRR.7",
		"n": "8758",
		"y": "MTA.Regional",
		"d": "Outbound",
		"os": [
			"MTA.LIRR.349"
		],
		"tt": [
			{
				"s": "MTA.LIRR.349",
				"d": "16:39"
			},
			{
				"s": "MTA.LIRR.214",
				"d": "16:51"
			},
			{
				"s": "MTA.LIRR.102",
				"d": "17:01"
			},
			{
				"s": "MTA.LIRR.119",
				"d": "17:07"
			},
			{
				"s": "MTA.LIRR.122",
				"d": "17:09"
			},
			{
				"s": "MTA.LIRR.180",
				"d": "17:12"
			},
			{
				"s": "MTA.LIRR.211",
				"d": "17:15"
			},
			{
				"s": "MTA.LIRR.66",
				"d": "17:19"
			},
			{
				"s": "MTA.LIRR.94",
				"d": "17:22"
			},
			{
				"s": "MTA.LIRR.217",
				"d": "17:24"
			},
			{
				"s": "MTA.LIRR.32",
				"d": "17:27"
			},
			{
				"s": "MTA.LIRR.114",
				"d": "17:29"
			},
			{
				"s": "MTA.LIRR.101",
				"d": "17:32"
			},
			{
				"s": "MTA.LIRR.65",
				"d": "17:37"
			}
		]
	},
	{
		"id": "MTA.LIRR.GO201_26_8760.Holiday",
		"t": "MTA.LIRR.GO201_26_8760",
		"r": "MTA.LIRR.7",
		"n": "8760",
		"y": "MTA.Regional",
		"d": "Outbound",
		"os": [
			"MTA.LIRR.349"
		],
		"tt": [
			{
				"s": "MTA.LIRR.349",
				"d": "17:39"
			},
			{
				"s": "MTA.LIRR.214",
				"d": "17:51"
			},
			{
				"s": "MTA.LIRR.102",
				"d": "18:01"
			},
			{
				"s": "MTA.LIRR.119",
				"d": "18:07"
			},
			{
				"s": "MTA.LIRR.122",
				"d": "18:09"
			},
			{
				"s": "MTA.LIRR.180",
				"d": "18:12"
			},
			{
				"s": "MTA.LIRR.211",
				"d": "18:15"
			},
			{
				"s": "MTA.LIRR.66",
				"d": "18:19"
			},
			{
				"s": "MTA.LIRR.94",
				"d": "18:22"
			},
			{
				"s": "MTA.LIRR.217",
				"d": "18:24"
			},
			{
				"s": "MTA.LIRR.32",
				"d": "18:27"
			},
			{
				"s": "MTA.LIRR.114",
				"d": "18:29"
			},
			{
				"s": "MTA.LIRR.101",
				"d": "18:32"
			},
			{
				"s": "MTA.LIRR.65",
				"d": "18:37"
			}
		]
	},
	{
		"id": "MTA.LIRR.GO201_26_8761.Holiday",
		"t": "MTA.LIRR.GO201_26_8761",
		"r": "MTA.LIRR.7",
		"n": "8761",
		"y": "MTA.Regional",
		"d": "Inbound",
		"os": [
			"MTA.LIRR.65"
		],
		"tt": [
			{
				"s": "MTA.LIRR.65",
				"d": "16:11"
			},
			{
				"s": "MTA.LIRR.101",
				"d": "16:16"
			},
			{
				"s": "MTA.LIRR.114",
				"d": "16:18"
			},
			{
				"s": "MTA.LIRR.32",
				"d": "16:20"
			},
			{
				"s": "MTA.LIRR.217",
				"d": "16:23"
			},
			{
				"s": "MTA.LIRR.94",
				"d": "16:25"
			},
			{
				"s": "MTA.LIRR.66",
				"d": "16:28"
			},
			{
				"s": "MTA.LIRR.211",
				"d": "16:32"
			},
			{
				"s": "MTA.LIRR.180",
				"d": "16:35"
			},
			{
				"s": "MTA.LIRR.122",
				"d": "16:38"
			},
			{
				"s": "MTA.LIRR.119",
				"d": "16:40"
			},
			{
				"s": "MTA.LIRR.102",
				"d": "16:48"
			},
			{
				"s": "MTA.LIRR.214",
				"d": "16:57"
			},
			{
				"s": "MTA.LIRR.349",
				"d": "17:08"
			}
		]
	},
	{
		"id": "MTA.LIRR.GO201_26_8762.Holiday",
		"t": "MTA.LIRR.GO201_26_8762",
		"r": "MTA.LIRR.7",
		"n": "8762",
		"y": "MTA.Regional",
		"d": "Outbound",
		"os": [
			"MTA.LIRR.349"
		],
		"tt": [
			{
				"s": "MTA.LIRR.349",
				"d": "18:39"
			},
			{
				"s": "MTA.LIRR.214",
				"d": "18:51"
			},
			{
				"s": "MTA.LIRR.102",
				"d": "19:01"
			},
			{
				"s": "MTA.LIRR.119",
				"d": "19:07"
			},
			{
				"s": "MTA.LIRR.122",
				"d": "19:09"
			},
			{
				"s": "MTA.LIRR.180",
				"d": "19:12"
			},
			{
				"s": "MTA.LIRR.211",
				"d": "19:15"
			},
			{
				"s": "MTA.LIRR.66",
				"d": "19:19"
			},
			{
				"s": "MTA.LIRR.94",
				"d": "19:22"
			},
			{
				"s": "MTA.LIRR.217",
				"d": "19:24"
			},
			{
				"s": "MTA.LIRR.32",
				"d": "19:27"
			},
			{
				"s": "MTA.LIRR.114",
				"d": "19:29"
			},
			{
				"s": "MTA.LIRR.101",
				"d": "19:32"
			},
			{
				"s": "MTA.LIRR.65",
				"d": "19:37"
			}
		]
	},
	{
		"id": "MTA.LIRR.GO201_26_8763.Holiday",
		"t": "MTA.LIRR.GO201_26_8763",
		"r": "MTA.LIRR.7",
		"n": "8763",
		"y": "MTA.Regional",
		"d": "Inbound",
		"os": [
			"MTA.LIRR.65"
		],
		"tt": [
			{
				"s": "MTA.LIRR.65",
				"d": "17:11"
			},
			{
				"s": "MTA.LIRR.101",
				"d": "17:16"
			},
			{
				"s": "MTA.LIRR.114",
				"d": "17:18"
			},
			{
				"s": "MTA.LIRR.32",
				"d": "17:20"
			},
			{
				"s": "MTA.LIRR.217",
				"d": "17:23"
			},
			{
				"s": "MTA.LIRR.94",
				"d": "17:25"
			},
			{
				"s": "MTA.LIRR.66",
				"d": "17:28"
			},
			{
				"s": "MTA.LIRR.211",
				"d": "17:32"
			},
			{
				"s": "MTA.LIRR.180",
				"d": "17:35"
			},
			{
				"s": "MTA.LIRR.122",
				"d": "17:38"
			},
			{
				"s": "MTA.LIRR.119",
				"d": "17:40"
			},
			{
				"s": "MTA.LIRR.102",
				"d": "17:48"
			},
			{
				"s": "MTA.LIRR.214",
				"d": "17:57"
			},
			{
				"s": "MTA.LIRR.349",
				"d": "18:08"
			}
		]
	},
	{
		"id": "MTA.LIRR.GO201_26_8764.Holiday",
		"t": "MTA.LIRR.GO201_26_8764",
		"r": "MTA.LIRR.7",
		"n": "8764",
		"y": "MTA.Regional",
		"d": "Outbound",
		"os": [
			"MTA.LIRR.349"
		],
		"tt": [
			{
				"s": "MTA.LIRR.349",
				"d": "19:39"
			},
			{
				"s": "MTA.LIRR.214",
				"d": "19:51"
			},
			{
				"s": "MTA.LIRR.102",
				"d": "20:01"
			},
			{
				"s": "MTA.LIRR.119",
				"d": "20:07"
			},
			{
				"s": "MTA.LIRR.122",
				"d": "20:09"
			},
			{
				"s": "MTA.LIRR.180",
				"d": "20:12"
			},
			{
				"s": "MTA.LIRR.211",
				"d": "20:15"
			},
			{
				"s": "MTA.LIRR.66",
				"d": "20:19"
			},
			{
				"s": "MTA.LIRR.94",
				"d": "20:22"
			},
			{
				"s": "MTA.LIRR.217",
				"d": "20:24"
			},
			{
				"s": "MTA.LIRR.32",
				"d": "20:27"
			},
			{
				"s": "MTA.LIRR.114",
				"d": "20:29"
			},
			{
				"s": "MTA.LIRR.101",
				"d": "20:32"
			},
			{
				"s": "MTA.LIRR.65",
				"d": "20:37"
			}
		]
	},
	{
		"id": "MTA.LIRR.GO201_26_8765.Holiday",
		"t": "MTA.LIRR.GO201_26_8765",
		"r": "MTA.LIRR.7",
		"n": "8765",
		"y": "MTA.Regional",
		"d": "Inbound",
		"os": [
			"MTA.LIRR.65"
		],
		"tt": [
			{
				"s": "MTA.LIRR.65",
				"d": "18:11"
			},
			{
				"s": "MTA.LIRR.101",
				"d": "18:16"
			},
			{
				"s": "MTA.LIRR.114",
				"d": "18:18"
			},
			{
				"s": "MTA.LIRR.32",
				"d": "18:20"
			},
			{
				"s": "MTA.LIRR.217",
				"d": "18:23"
			},
			{
				"s": "MTA.LIRR.94",
				"d": "18:25"
			},
			{
				"s": "MTA.LIRR.66",
				"d": "18:28"
			},
			{
				"s": "MTA.LIRR.211",
				"d": "18:32"
			},
			{
				"s": "MTA.LIRR.180",
				"d": "18:35"
			},
			{
				"s": "MTA.LIRR.122",
				"d": "18:38"
			},
			{
				"s": "MTA.LIRR.119",
				"d": "18:40"
			},
			{
				"s": "MTA.LIRR.102",
				"d": "18:48"
			},
			{
				"s": "MTA.LIRR.214",
				"d": "18:57"
			},
			{
				"s": "MTA.LIRR.349",
				"d": "19:08"
			}
		]
	},
	{
		"id": "MTA.LIRR.GO201_26_8766.Holiday",
		"t": "MTA.LIRR.GO201_26_8766",
		"r": "MTA.LIRR.7",
		"n": "8766",
		"y": "MTA.Regional",
		"d": "Outbound",
		"os": [
			"MTA.LIRR.349"
		],
		"tt": [
			{
				"s": "MTA.LIRR.349",
				"d": "20:39"
			},
			{
				"s": "MTA.LIRR.214",
				"d": "20:51"
			},
			{
				"s": "MTA.LIRR.102",
				"d": "21:01"
			},
			{
				"s": "MTA.LIRR.119",
				"d": "21:07"
			},
			{
				"s": "MTA.LIRR.122",
				"d": "21:09"
			},
			{
				"s": "MTA.LIRR.180",
				"d": "21:12"
			},
			{
				"s": "MTA.LIRR.211",
				"d": "21:15"
			},
			{
				"s": "MTA.LIRR.66",
				"d": "21:19"
			},
			{
				"s": "MTA.LIRR.94",
				"d": "21:22"
			},
			{
				"s": "MTA.LIRR.217",
				"d": "21:24"
			},
			{
				"s": "MTA.LIRR.32",
				"d": "21:27"
			},
			{
				"s": "MTA.LIRR.114",
				"d": "21:29"
			},
			{
				"s": "MTA.LIRR.101",
				"d": "21:32"
			},
			{
				"s": "MTA.LIRR.65",
				"d": "21:37"
			}
		]
	},
	{
		"id": "MTA.LIRR.GO201_26_8767.Holiday",
		"t": "MTA.LIRR.GO201_26_8767",
		"r": "MTA.LIRR.7",
		"n": "8767",
		"y": "MTA.Regional",
		"d": "Inbound",
		"os": [
			"MTA.LIRR.65"
		],
		"tt": [
			{
				"s": "MTA.LIRR.65",
				"d": "19:11"
			},
			{
				"s": "MTA.LIRR.101",
				"d": "19:16"
			},
			{
				"s": "MTA.LIRR.114",
				"d": "19:18"
			},
			{
				"s": "MTA.LIRR.32",
				"d": "19:20"
			},
			{
				"s": "MTA.LIRR.217",
				"d": "19:23"
			},
			{
				"s": "MTA.LIRR.94",
				"d": "19:25"
			},
			{
				"s": "MTA.LIRR.66",
				"d": "19:28"
			},
			{
				"s": "MTA.LIRR.211",
				"d": "19:32"
			},
			{
				"s": "MTA.LIRR.180",
				"d": "19:35"
			},
			{
				"s": "MTA.LIRR.122",
				"d": "19:38"
			},
			{
				"s": "MTA.LIRR.119",
				"d": "19:40"
			},
			{
				"s": "MTA.LIRR.102",
				"d": "19:48"
			},
			{
				"s": "MTA.LIRR.214",
				"d": "19:57"
			},
			{
				"s": "MTA.LIRR.349",
				"d": "20:08"
			}
		]
	},
	{
		"id": "MTA.LIRR.GO201_26_8768.Holiday",
		"t": "MTA.LIRR.GO201_26_8768",
		"r": "MTA.LIRR.7",
		"n": "8768",
		"y": "MTA.Regional",
		"d": "Outbound",
		"os": [
			"MTA.LIRR.349"
		],
		"tt": [
			{
				"s": "MTA.LIRR.349",
				"d": "21:39"
			},
			{
				"s": "MTA.LIRR.214",
				"d": "21:51"
			},
			{
				"s": "MTA.LIRR.102",
				"d": "22:01"
			},
			{
				"s": "MTA.LIRR.119",
				"d": "22:07"
			},
			{
				"s": "MTA.LIRR.122",
				"d": "22:09"
			},
			{
				"s": "MTA.LIRR.180",
				"d": "22:12"
			},
			{
				"s": "MTA.LIRR.211",
				"d": "22:15"
			},
			{
				"s": "MTA.LIRR.66",
				"d": "22:19"
			},
			{
				"s": "MTA.LIRR.94",
				"d": "22:22"
			},
			{
				"s": "MTA.LIRR.217",
				"d": "22:24"
			},
			{
				"s": "MTA.LIRR.32",
				"d": "22:27"
			},
			{
				"s": "MTA.LIRR.114",
				"d": "22:29"
			},
			{
				"s": "MTA.LIRR.101",
				"d": "22:32"
			},
			{
				"s": "MTA.LIRR.65",
				"d": "22:37"
			}
		]
	},
	{
		"id": "MTA.LIRR.GO201_26_8769.Holiday",
		"t": "MTA.LIRR.GO201_26_8769",
		"r": "MTA.LIRR.7",
		"n": "8769",
		"y": "MTA.Regional",
		"d": "Inbound",
		"os": [
			"MTA.LIRR.65"
		],
		"tt": [
			{
				"s": "MTA.LIRR.65",
				"d": "20:07"
			},
			{
				"s": "MTA.LIRR.101",
				"d": "20:12"
			},
			{
				"s": "MTA.LIRR.114",
				"d": "20:14"
			},
			{
				"s": "MTA.LIRR.32",
				"d": "20:16"
			},
			{
				"s": "MTA.LIRR.217",
				"d": "20:19"
			},
			{
				"s": "MTA.LIRR.94",
				"d": "20:21"
			},
			{
				"s": "MTA.LIRR.66",
				"d": "20:24"
			},
			{
				"s": "MTA.LIRR.211",
				"d": "20:28"
			},
			{
				"s": "MTA.LIRR.180",
				"d": "20:31"
			},
			{
				"s": "MTA.LIRR.122",
				"d": "20:34"
			},
			{
				"s": "MTA.LIRR.119",
				"d": "20:36"
			},
			{
				"s": "MTA.LIRR.102",
				"d": "20:44"
			},
			{
				"s": "MTA.LIRR.214",
				"d": "20:53"
			},
			{
				"s": "MTA.LIRR.349",
				"d": "21:04"
			}
		]
	},
	{
		"id": "MTA.LIRR.GO201_26_8770.Holiday",
		"t": "MTA.LIRR.GO201_26_8770",
		"r": "MTA.LIRR.7",
		"n": "8770",
		"y": "MTA.Regional",
		"d": "Outbound",
		"os": [
			"MTA.LIRR.349"
		],
		"tt": [
			{
				"s": "MTA.LIRR.349",
				"d": "22:39"
			},
			{
				"s": "MTA.LIRR.214",
				"d": "22:51"
			},
			{
				"s": "MTA.LIRR.102",
				"d": "23:01"
			},
			{
				"s": "MTA.LIRR.119",
				"d": "23:07"
			},
			{
				"s": "MTA.LIRR.122",
				"d": "23:09"
			},
			{
				"s": "MTA.LIRR.180",
				"d": "23:12"
			},
			{
				"s": "MTA.LIRR.211",
				"d": "23:15"
			},
			{
				"s": "MTA.LIRR.66",
				"d": "23:19"
			},
			{
				"s": "MTA.LIRR.94",
				"d": "23:22"
			},
			{
				"s": "MTA.LIRR.217",
				"d": "23:24"
			},
			{
				"s": "MTA.LIRR.32",
				"d": "23:27"
			},
			{
				"s": "MTA.LIRR.114",
				"d": "23:29"
			},
			{
				"s": "MTA.LIRR.101",
				"d": "23:32"
			},
			{
				"s": "MTA.LIRR.65",
				"d": "23:37"
			}
		]
	},
	{
		"id": "MTA.LIRR.GO201_26_8772.Holiday",
		"t": "MTA.LIRR.GO201_26_8772",
		"r": "MTA.LIRR.7",
		"n": "8772",
		"y": "MTA.Regional",
		"d": "Outbound",
		"os": [
			"MTA.LIRR.349"
		],
		"tt": [
			{
				"s": "MTA.LIRR.349",
				"d": "23:39"
			},
			{
				"s": "MTA.LIRR.214",
				"d": "23:51"
			},
			{
				"s": "MTA.LIRR.102",
				"d": "24:00"
			},
			{
				"s": "MTA.LIRR.119",
				"d": "24:06"
			},
			{
				"s": "MTA.LIRR.122",
				"d": "24:08"
			},
			{
				"s": "MTA.LIRR.180",
				"d": "24:11"
			},
			{
				"s": "MTA.LIRR.211",
				"d": "24:14"
			},
			{
				"s": "MTA.LIRR.66",
				"d": "24:18"
			},
			{
				"s": "MTA.LIRR.94",
				"d": "24:20"
			},
			{
				"s": "MTA.LIRR.217",
				"d": "24:22"
			},
			{
				"s": "MTA.LIRR.32",
				"d": "24:25"
			},
			{
				"s": "MTA.LIRR.114",
				"d": "24:27"
			},
			{
				"s": "MTA.LIRR.101",
				"d": "24:29"
			},
			{
				"s": "MTA.LIRR.65",
				"d": "24:34"
			}
		]
	},
	{
		"id": "MTA.LIRR.GO201_26_8773.Holiday",
		"t": "MTA.LIRR.GO201_26_8773",
		"r": "MTA.LIRR.7",
		"n": "8773",
		"y": "MTA.Regional",
		"d": "Inbound",
		"os": [
			"MTA.LIRR.65"
		],
		"tt": [
			{
				"s": "MTA.LIRR.65",
				"d": "21:11"
			},
			{
				"s": "MTA.LIRR.101",
				"d": "21:16"
			},
			{
				"s": "MTA.LIRR.114",
				"d": "21:18"
			},
			{
				"s": "MTA.LIRR.32",
				"d": "21:20"
			},
			{
				"s": "MTA.LIRR.217",
				"d": "21:23"
			},
			{
				"s": "MTA.LIRR.94",
				"d": "21:25"
			},
			{
				"s": "MTA.LIRR.66",
				"d": "21:28"
			},
			{
				"s": "MTA.LIRR.211",
				"d": "21:32"
			},
			{
				"s": "MTA.LIRR.180",
				"d": "21:35"
			},
			{
				"s": "MTA.LIRR.122",
				"d": "21:38"
			},
			{
				"s": "MTA.LIRR.119",
				"d": "21:40"
			},
			{
				"s": "MTA.LIRR.102",
				"d": "21:48"
			},
			{
				"s": "MTA.LIRR.214",
				"d": "21:57"
			},
			{
				"s": "MTA.LIRR.349",
				"d": "22:07"
			}
		]
	},
	{
		"id": "MTA.LIRR.GO201_26_8775.Holiday",
		"t": "MTA.LIRR.GO201_26_8775",
		"r": "MTA.LIRR.7",
		"n": "8775",
		"y": "MTA.Regional",
		"d": "Inbound",
		"os": [
			"MTA.LIRR.65"
		],
		"tt": [
			{
				"s": "MTA.LIRR.65",
				"d": "22:07"
			},
			{
				"s": "MTA.LIRR.101",
				"d": "22:12"
			},
			{
				"s": "MTA.LIRR.114",
				"d": "22:14"
			},
			{
				"s": "MTA.LIRR.32",
				"d": "22:16"
			},
			{
				"s": "MTA.LIRR.217",
				"d": "22:19"
			},
			{
				"s": "MTA.LIRR.94",
				"d": "22:21"
			},
			{
				"s": "MTA.LIRR.66",
				"d": "22:24"
			},
			{
				"s": "MTA.LIRR.211",
				"d": "22:28"
			},
			{
				"s": "MTA.LIRR.180",
				"d": "22:31"
			},
			{
				"s": "MTA.LIRR.122",
				"d": "22:34"
			},
			{
				"s": "MTA.LIRR.119",
				"d": "22:36"
			},
			{
				"s": "MTA.LIRR.102",
				"d": "22:44"
			},
			{
				"s": "MTA.LIRR.214",
				"d": "22:53"
			},
			{
				"s": "MTA.LIRR.349",
				"d": "23:04"
			}
		]
	},
	{
		"id": "MTA.LIRR.GO201_26_8777.Holiday",
		"t": "MTA.LIRR.GO201_26_8777",
		"r": "MTA.LIRR.7",
		"n": "8777",
		"y": "MTA.Regional",
		"d": "Inbound",
		"os": [
			"MTA.LIRR.65"
		],
		"tt": [
			{
				"s": "MTA.LIRR.65",
				"d": "23:07"
			},
			{
				"s": "MTA.LIRR.101",
				"d": "23:12"
			},
			{
				"s": "MTA.LIRR.114",
				"d": "23:14"
			},
			{
				"s": "MTA.LIRR.32",
				"d": "23:16"
			},
			{
				"s": "MTA.LIRR.217",
				"d": "23:19"
			},
			{
				"s": "MTA.LIRR.94",
				"d": "23:21"
			},
			{
				"s": "MTA.LIRR.66",
				"d": "23:24"
			},
			{
				"s": "MTA.LIRR.211",
				"d": "23:28"
			},
			{
				"s": "MTA.LIRR.180",
				"d": "23:31"
			},
			{
				"s": "MTA.LIRR.122",
				"d": "23:34"
			},
			{
				"s": "MTA.LIRR.119",
				"d": "23:36"
			},
			{
				"s": "MTA.LIRR.102",
				"d": "23:44"
			},
			{
				"s": "MTA.LIRR.214",
				"d": "23:53"
			},
			{
				"s": "MTA.LIRR.349",
				"d": "24:04"
			}
		]
	}
]